PI-Filter/lock_detector.v
module lock_detector(
    input  wire        clk,
    input  wire        rst_n,
    input  wire signed [11:0] error,

    output reg         lock
);

parameter THRESHOLD  = 12'd8;
parameter LOCK_COUNT = 6'd32;

reg [5:0] counter;

wire signed [11:0] abs_error =
        error[11] ? -error : error;

always @(posedge clk or negedge rst_n) begin
    if(!rst_n) begin
        counter <= 0;
        lock    <= 0;
    end
    else begin
        if(abs_error <= THRESHOLD) begin
            if(counter < LOCK_COUNT)
                counter <= counter + 1;
        end
        else begin
            counter <= 0;
            lock    <= 0;
        end

        if(counter >= LOCK_COUNT-1)
            lock <= 1;
    end
end

endmodule

PI-Filter/pi_filter.v
`timescale 1ns/1ps

// TB to be run with gain scheduler

module pi_loop_filter #(
    parameter ERR_W      = 12,
    parameter GAIN_W     = 32,
    parameter ACCUM_W    = 32,
    parameter FRAC_BITS  = 16,
    parameter OUT_W      = 16,

    parameter signed [ACCUM_W-1:0] PRELOAD   = -32'sd3000,

    parameter signed [ACCUM_W-1:0] INTEG_MAX = 32'sd2147483647,
    parameter signed [ACCUM_W-1:0] INTEG_MIN = -32'sd2147483647
)(
    input  wire clk,
    input  wire rst_n,

    input  wire signed [ERR_W-1:0] error,

    input  wire signed [GAIN_W-1:0] kp,
    input  wire signed [GAIN_W-1:0] ki,

    output reg signed [OUT_W-1:0] ctrl_word
);

    //--------------------------------------------------
    // State
    //--------------------------------------------------
    reg signed [ACCUM_W-1:0] integrator;
    reg signed [ACCUM_W-1:0] ctrl_word_q;

    //--------------------------------------------------
    // Full-width multipliers
    //--------------------------------------------------
    wire signed [ERR_W+GAIN_W-1:0] p_mult;
    wire signed [ERR_W+GAIN_W-1:0] i_mult;

    assign p_mult = $signed(error) * $signed(kp);
    assign i_mult = $signed(error) * $signed(ki);

    //--------------------------------------------------
    // Fixed-point scaling
    //--------------------------------------------------
    wire signed [ACCUM_W-1:0] p_term;
    wire signed [ACCUM_W-1:0] i_term;

    assign p_term = p_mult >>> FRAC_BITS;
    assign i_term = i_mult >>> FRAC_BITS;

    //--------------------------------------------------
    // Python:
    // integrator -= Ki*error
    //--------------------------------------------------
    wire signed [ACCUM_W-1:0] integrator_next;

    assign integrator_next = integrator - i_term;

    //--------------------------------------------------
    // Python:
    // pi_out = integrator - Kp*error
    //--------------------------------------------------
    wire signed [ACCUM_W-1:0] pi_out;

    assign pi_out = integrator_next - p_term;

    //--------------------------------------------------
    // alpha = 0.625 (5/8)
    // beta  = 0.375 (3/8)
    //--------------------------------------------------
    wire signed [ACCUM_W-1:0] alpha_term;
    wire signed [ACCUM_W-1:0] beta_term;
    wire signed [ACCUM_W-1:0] ctrl_next;

    assign alpha_term = ((pi_out <<< 2) + pi_out) >>> 3;
    assign beta_term  = ((ctrl_word_q <<< 1) + ctrl_word_q) >>> 3;

    assign ctrl_next = alpha_term + beta_term;

    //--------------------------------------------------
    // Sequential Logic
    //--------------------------------------------------
    always @(posedge clk or negedge rst_n) begin
        if (!rst_n) begin
            integrator  <= PRELOAD;
            ctrl_word_q <= PRELOAD;
            ctrl_word   <= PRELOAD[OUT_W-1:0];
        end
        else begin

            //------------------------------------------
            // Integrator anti-windup
            //------------------------------------------
            if (integrator_next > INTEG_MAX)
                integrator <= INTEG_MAX;
            else if (integrator_next < INTEG_MIN)
                integrator <= INTEG_MIN;
            else
                integrator <= integrator_next;

            //------------------------------------------
            // Control word smoothing
            //------------------------------------------
            ctrl_word_q <= ctrl_next;

            //------------------------------------------
            // Output saturation
            //------------------------------------------
            if (ctrl_next > 32767)
                ctrl_word <= 16'sd32767;
            else if (ctrl_next < -32768)
                ctrl_word <= -16'sd32768;
            else
                ctrl_word <= ctrl_next[OUT_W-1:0];
        end
    end

endmodule

ADPLL_Integrated/gain_scheduler.v
`timescale 1ns/1ps
module gain_scheduler #(

    // Fast acquisition mode (bw_scale = 10)
    parameter signed [31:0] KP_FAST = 32'd2957967,
    parameter signed [31:0] KI_FAST = 32'd49197,

    // Medium bandwidth mode (bw_scale = 3)
    parameter signed [31:0] KP_MED  = 32'd887390,
    parameter signed [31:0] KI_MED  = 32'd4428,

    // Tracking mode (bw_scale = 1)
    parameter signed [31:0] KP_SLOW = 32'd295797,
    parameter signed [31:0] KI_SLOW = 32'd492,

    // ── CORRECTED COUNTER END POINTS (Feedback Cycles) ──
    // Python threshold 2500 / DECIM 4 = 625
    parameter FAST_END = 16'd625,  
    
    // Python threshold 3500 / DECIM 4 = 875
    parameter MED_END  = 16'd875   

)(
    input  wire [15:0] counter,
    output reg signed [31:0] kp,
    output reg signed [31:0] ki
);

always @(*) begin

    if(counter < FAST_END) begin
        kp = KP_FAST;
        ki = KI_FAST;
    end
    else if(counter < MED_END) begin
        kp = KP_MED;
        ki = KI_MED;
    end
    else begin
        kp = KP_SLOW;
        ki = KI_SLOW;
    end

end
endmodule

PI-Filter/tb_adpll_loop_filter.v
`timescale 1ns/1ps

module tb_adpll_loop_filter;

    //--------------------------------------------------
    // Clock
    //--------------------------------------------------
    reg clk = 0;
    always #5 clk = ~clk;      // 100 MHz

    //--------------------------------------------------
    // Reset
    //--------------------------------------------------
    reg rst_n;

    //--------------------------------------------------
    // TDC error
    //--------------------------------------------------
    reg signed [11:0] error;

    //--------------------------------------------------
    // Scheduler outputs
    //--------------------------------------------------
    reg [15:0] counter;
    wire signed [31:0] kp;
    wire signed [31:0] ki;

    //--------------------------------------------------
    // PI output
    //--------------------------------------------------
    wire signed [15:0] ctrl_word;

    //--------------------------------------------------
    // DUT 1 : Gain Scheduler
    //--------------------------------------------------
    gain_scheduler scheduler (
    .counter(counter),
    .kp(kp),
    .ki(ki)
);

    //--------------------------------------------------
    // DUT 2 : PI Filter
    //--------------------------------------------------
    pi_loop_filter filter (
        .clk       (clk),
        .rst_n     (rst_n),
        .error     (error),
        .kp        (kp),
        .ki        (ki),
        .ctrl_word (ctrl_word)
    );
     wire lock;

    lock_detector u_lock (
    .clk   (clk),
    .rst_n (rst_n),
    .error (error),      // TDC output
    .lock  (lock)
     );
    //--------------------------------------------------
    // Monitor
    //--------------------------------------------------
    initial begin
        $display("time\t err\t kp\t ki\t ctrl\t lock");

        $monitor("%0t\t%d\t%d\t%d\t%d\t%b",
                 $time,
                 error,
                 kp,
                 ki,
                 ctrl_word,
                 lock );
    end

    //--------------------------------------------------
    // Stimulus
    //--------------------------------------------------
    integer i;
    always @(posedge clk or negedge rst_n) begin
    if(!rst_n)
        counter <= 0;
    else
        counter <= counter + 1;
end

    initial begin

        rst_n = 0;
        error = 0;

        repeat(5) @(posedge clk);

        rst_n = 1;

        //----------------------------------------------
        // Acquisition
        //----------------------------------------------
        for(i=0;i<50;i=i+1) begin
            @(posedge clk);
            error <= 20;
        end

        //----------------------------------------------
        // Convergence
        //----------------------------------------------
        for(i=0;i<50;i=i+1) begin
            @(posedge clk);
            error <= 5;
        end

        //----------------------------------------------
        // Near lock
        //----------------------------------------------
        for(i=0;i<50;i=i+1) begin
            @(posedge clk);
            error <= 1;
        end

        //----------------------------------------------
        // Locked
        //----------------------------------------------
        for(i=0;i<100;i=i+1) begin
            @(posedge clk);

            case(i % 3)
                0: error <= 0;
                1: error <= 1;
                2: error <= -1;
            endcase
        end

        //----------------------------------------------
        // Disturbance
        //----------------------------------------------
        for(i=0;i<30;i=i+1) begin
            @(posedge clk);
            error <= 12;
        end

        //----------------------------------------------
        // Re-lock
        //----------------------------------------------
        for(i=0;i<80;i=i+1) begin
            @(posedge clk);
            error <= 0;
        end

        $finish;
    end
always @(posedge clk) begin
    $display("counter=%0d kp=%0d ki=%0d",
             counter, kp, ki);
end
    //--------------------------------------------------
    // Wave dump
    //--------------------------------------------------
    initial begin
        $dumpfile("adpll_loop_filter.vcd");
        $dumpvars(0,tb_adpll_loop_filter);
    end

endmodule

PI-Filter/adpll_loop_filter.vcd
$date
	Fri Jun 19 21:58:40 2026
$end
$version
	Icarus Verilog
$end
$timescale
	1ps
$end
$scope module tb_adpll_loop_filter $end
$var wire 1 ! lock $end
$var wire 32 " kp [31:0] $end
$var wire 32 # ki [31:0] $end
$var wire 16 $ ctrl_word [15:0] $end
$var reg 1 % clk $end
$var reg 16 & counter [15:0] $end
$var reg 12 ' error [11:0] $end
$var reg 1 ( rst_n $end
$var integer 32 ) i [31:0] $end
$scope module filter $end
$var wire 1 % clk $end
$var wire 12 * error [11:0] $end
$var wire 1 ( rst_n $end
$var wire 32 + pi_out [31:0] $end
$var wire 32 , p_term [31:0] $end
$var wire 44 - p_mult [43:0] $end
$var wire 32 . kp [31:0] $end
$var wire 32 / ki [31:0] $end
$var wire 32 0 integrator_next [31:0] $end
$var wire 32 1 i_term [31:0] $end
$var wire 44 2 i_mult [43:0] $end
$var wire 32 3 ctrl_next [31:0] $end
$var wire 32 4 beta_term [31:0] $end
$var wire 32 5 alpha_term [31:0] $end
$var parameter 32 6 ACCUM_W $end
$var parameter 32 7 ERR_W $end
$var parameter 32 8 FRAC_BITS $end
$var parameter 32 9 GAIN_W $end
$var parameter 32 : INTEG_MAX $end
$var parameter 32 ; INTEG_MIN $end
$var parameter 32 < OUT_W $end
$var parameter 32 = PRELOAD $end
$var reg 16 > ctrl_word [15:0] $end
$var reg 32 ? ctrl_word_q [31:0] $end
$var reg 32 @ integrator [31:0] $end
$upscope $end
$scope module scheduler $end
$var wire 16 A counter [15:0] $end
$var parameter 32 B FAST_END $end
$var parameter 32 C KI_FAST $end
$var parameter 32 D KI_MED $end
$var parameter 32 E KI_SLOW $end
$var parameter 32 F KP_FAST $end
$var parameter 32 G KP_MED $end
$var parameter 32 H KP_SLOW $end
$var parameter 32 I MED_END $end
$var reg 32 J ki [31:0] $end
$var reg 32 K kp [31:0] $end
$upscope $end
$scope module u_lock $end
$var wire 1 % clk $end
$var wire 12 L error [11:0] $end
$var wire 1 ( rst_n $end
$var wire 12 M abs_error [11:0] $end
$var parameter 6 N LOCK_COUNT $end
$var parameter 12 O THRESHOLD $end
$var reg 6 P counter [5:0] $end
$var reg 1 ! lock $end
$upscope $end
$upscope $end
$enddefinitions $end
$comment Show the parameter values. $end
$dumpall
b1000 O
b100000 N
b1100100 I
b1001000001101110101 H
b11011000101001011110 G
b1011010010001010001111 F
b111101100 E
b1000101001100 D
b1100000000101101 C
b110010 B
b11111111111111111111010001001000 =
b10000 <
b10000000000000000000000000000001 ;
b1111111111111111111111111111111 :
b100000 9
b10000 8
b1100 7
b100000 6
$end
#0
$dumpvars
b0 P
b0 M
b0 L
b1011010010001010001111 K
b1100000000101101 J
b0 A
b11111111111111111111010001001000 @
b11111111111111111111010001001000 ?
b1111010001001000 >
b11111111111111111111100010101101 5
b11111111111111111111101110011011 4
b11111111111111111111010001001000 3
b0 2
b0 1
b11111111111111111111010001001000 0
b1100000000101101 /
b1011010010001010001111 .
b0 -
b0 ,
b11111111111111111111010001001000 +
b0 *
bx )
0(
b0 '
b0 &
0%
b1111010001001000 $
b1100000000101101 #
b1011010010001010001111 "
0!
$end
#5000
1%
#10000
0%
#15000
1%
#20000
0%
#25000
1%
#30000
0%
#35000
1%
#40000
0%
#45000
b1 &
b1 A
b1 P
b0 )
1(
1%
#50000
0%
#55000
b11111111111111111111001000001010 3
b11111111111111111111011001101111 5
b1110000110 ,
b11111111111111111111000010110011 +
b11111111111111111111010000111001 0
b1111 1
b10100 M
b10 P
b10 &
b10 A
b11100001101011001100101100 -
b11110000001110000100 2
b10100 '
b10100 *
b10100 L
b1 )
1%
#60000
0%
#65000
b11111111111111111111101011000011 4
b11111111111111111111000100101001 3
b11111111111111111111011001100110 5
b11 &
b11 A
b0 P
b1111001000001010 $
b1111001000001010 >
b11111111111111111111001000001010 ?
b11111111111111111111000010100100 +
b11111111111111111111010000101010 0
b11111111111111111111010000111001 @
b10 )
1%
#70000
0%
#75000
b11111111111111111111101001101111 4
b11111111111111111111000011001100 3
b11111111111111111111011001011101 5
b1111000100101001 $
b1111000100101001 >
b11111111111111111111000100101001 ?
b11111111111111111111000010010101 +
b11111111111111111111010000011011 0
b11111111111111111111010000101010 @
b100 &
b100 A
b11 )
1%
#80000
0%
#85000
b11111111111111111111101001001100 4
b11111111111111111111000010011111 3
b11111111111111111111011001010011 5
b101 &
b101 A
b1111000011001100 $
b1111000011001100 >
b11111111111111111111000011001100 ?
b11111111111111111111000010000110 +
b11111111111111111111010000001100 0
b11111111111111111111010000011011 @
b100 )
1%
#90000
0%
#95000
b11111111111111111111101000111011 4
b11111111111111111111000010000101 3
b11111111111111111111011001001010 5
b1111000010011111 $
b1111000010011111 >
b11111111111111111111000010011111 ?
b11111111111111111111000001110111 +
b11111111111111111111001111111101 0
b11111111111111111111010000001100 @
b110 &
b110 A
b101 )
1%
#100000
0%
#105000
b11111111111111111111101000110001 4
b11111111111111111111000001110010 3
b11111111111111111111011001000001 5
b111 &
b111 A
b1111000010000101 $
b1111000010000101 >
b11111111111111111111000010000101 ?
b11111111111111111111000001101000 +
b11111111111111111111001111101110 0
b11111111111111111111001111111101 @
b110 )
1%
#110000
0%
#115000
b11111111111111111111101000101010 4
b11111111111111111111000001100001 3
b11111111111111111111011000110111 5
b1111000001110010 $
b1111000001110010 >
b11111111111111111111000001110010 ?
b11111111111111111111000001011001 +
b11111111111111111111001111011111 0
b11111111111111111111001111101110 @
b1000 &
b1000 A
b111 )
1%
#120000
0%
#125000
b11111111111111111111101000100100 4
b11111111111111111111000001010010 3
b11111111111111111111011000101110 5
b1001 &
b1001 A
b1111000001100001 $
b1111000001100001 >
b11111111111111111111000001100001 ?
b11111111111111111111000001001010 +
b11111111111111111111001111010000 0
b11111111111111111111001111011111 @
b1000 )
1%
#130000
0%
#135000
b11111111111111111111101000011110 4
b11111111111111111111000001000010 3
b11111111111111111111011000100100 5
b1111000001010010 $
b1111000001010010 >
b11111111111111111111000001010010 ?
b11111111111111111111000000111011 +
b11111111111111111111001111000001 0
b11111111111111111111001111010000 @
b1010 &
b1010 A
b1001 )
1%
#140000
0%
#145000
b11111111111111111111101000011000 4
b11111111111111111111000000110011 3
b11111111111111111111011000011011 5
b1011 &
b1011 A
b1111000001000010 $
b1111000001000010 >
b11111111111111111111000001000010 ?
b11111111111111111111000000101100 +
b11111111111111111111001110110010 0
b11111111111111111111001111000001 @
b1010 )
1%
#150000
0%
#155000
b11111111111111111111101000010011 4
b11111111111111111111000000100101 3
b11111111111111111111011000010010 5
b1111000000110011 $
b1111000000110011 >
b11111111111111111111000000110011 ?
b11111111111111111111000000011101 +
b11111111111111111111001110100011 0
b11111111111111111111001110110010 @
b1100 &
b1100 A
b1011 )
1%
#160000
0%
#165000
b11111111111111111111101000001101 4
b11111111111111111111000000010101 3
b11111111111111111111011000001000 5
b1101 &
b1101 A
b1111000000100101 $
b1111000000100101 >
b11111111111111111111000000100101 ?
b11111111111111111111000000001110 +
b11111111111111111111001110010100 0
b11111111111111111111001110100011 @
b1100 )
1%
#170000
0%
#175000
b11111111111111111111101000000111 4
b11111111111111111111000000000110 3
b11111111111111111111010111111111 5
b1111000000010101 $
b1111000000010101 >
b11111111111111111111000000010101 ?
b11111111111111111110111111111111 +
b11111111111111111111001110000101 0
b11111111111111111111001110010100 @
b1110 &
b1110 A
b1101 )
1%
#180000
0%
#185000
b11111111111111111111101000000010 4
b11111111111111111110111111111000 3
b11111111111111111111010111110110 5
b1111 &
b1111 A
b1111000000000110 $
b1111000000000110 >
b11111111111111111111000000000110 ?
b11111111111111111110111111110000 +
b11111111111111111111001101110110 0
b11111111111111111111001110000101 @
b1110 )
1%
#190000
0%
#195000
b11111111111111111111100111111101 4
b11111111111111111110111111101001 3
b11111111111111111111010111101100 5
b1110111111111000 $
b1110111111111000 >
b11111111111111111110111111111000 ?
b11111111111111111110111111100001 +
b11111111111111111111001101100111 0
b11111111111111111111001101110110 @
b10000 &
b10000 A
b1111 )
1%
#200000
0%
#205000
b11111111111111111111100111110111 4
b11111111111111111110111111011010 3
b11111111111111111111010111100011 5
b10001 &
b10001 A
b1110111111101001 $
b1110111111101001 >
b11111111111111111110111111101001 ?
b11111111111111111110111111010010 +
b11111111111111111111001101011000 0
b11111111111111111111001101100111 @
b10000 )
1%
#210000
0%
#215000
b11111111111111111111100111110001 4
b11111111111111111110111111001010 3
b11111111111111111111010111011001 5
b1110111111011010 $
b1110111111011010 >
b11111111111111111110111111011010 ?
b11111111111111111110111111000011 +
b11111111111111111111001101001001 0
b11111111111111111111001101011000 @
b10010 &
b10010 A
b10001 )
1%
#220000
0%
#225000
b11111111111111111111100111101011 4
b11111111111111111110111110111011 3
b11111111111111111111010111010000 5
b10011 &
b10011 A
b1110111111001010 $
b1110111111001010 >
b11111111111111111110111111001010 ?
b11111111111111111110111110110100 +
b11111111111111111111001100111010 0
b11111111111111111111001101001001 @
b10010 )
1%
#230000
0%
#235000
b11111111111111111111100111100110 4
b11111111111111111110111110101101 3
b11111111111111111111010111000111 5
b1110111110111011 $
b1110111110111011 >
b11111111111111111110111110111011 ?
b11111111111111111110111110100101 +
b11111111111111111111001100101011 0
b11111111111111111111001100111010 @
b10100 &
b10100 A
b10011 )
1%
#240000
0%
#245000
b11111111111111111111100111100000 4
b11111111111111111110111110011101 3
b11111111111111111111010110111101 5
b10101 &
b10101 A
b1110111110101101 $
b1110111110101101 >
b11111111111111111110111110101101 ?
b11111111111111111110111110010110 +
b11111111111111111111001100011100 0
b11111111111111111111001100101011 @
b10100 )
1%
#250000
0%
#255000
b11111111111111111111100111011010 4
b11111111111111111110111110001110 3
b11111111111111111111010110110100 5
b1110111110011101 $
b1110111110011101 >
b11111111111111111110111110011101 ?
b11111111111111111110111110000111 +
b11111111111111111111001100001101 0
b11111111111111111111001100011100 @
b10110 &
b10110 A
b10101 )
1%
#260000
0%
#265000
b11111111111111111111100111010101 4
b11111111111111111110111110000000 3
b11111111111111111111010110101011 5
b10111 &
b10111 A
b1110111110001110 $
b1110111110001110 >
b11111111111111111110111110001110 ?
b11111111111111111110111101111000 +
b11111111111111111111001011111110 0
b11111111111111111111001100001101 @
b10110 )
1%
#270000
0%
#275000
b11111111111111111111100111010000 4
b11111111111111111110111101110001 3
b11111111111111111111010110100001 5
b1110111110000000 $
b1110111110000000 >
b11111111111111111110111110000000 ?
b11111111111111111110111101101001 +
b11111111111111111111001011101111 0
b11111111111111111111001011111110 @
b11000 &
b11000 A
b10111 )
1%
#280000
0%
#285000
b11111111111111111111100111001010 4
b11111111111111111110111101100010 3
b11111111111111111111010110011000 5
b11001 &
b11001 A
b1110111101110001 $
b1110111101110001 >
b11111111111111111110111101110001 ?
b11111111111111111110111101011010 +
b11111111111111111111001011100000 0
b11111111111111111111001011101111 @
b11000 )
1%
#290000
0%
#295000
b11111111111111111111100111000100 4
b11111111111111111110111101010010 3
b11111111111111111111010110001110 5
b1110111101100010 $
b1110111101100010 >
b11111111111111111110111101100010 ?
b11111111111111111110111101001011 +
b11111111111111111111001011010001 0
b11111111111111111111001011100000 @
b11010 &
b11010 A
b11001 )
1%
#300000
0%
#305000
b11111111111111111111100110111110 4
b11111111111111111110111101000011 3
b11111111111111111111010110000101 5
b11011 &
b11011 A
b1110111101010010 $
b1110111101010010 >
b11111111111111111110111101010010 ?
b11111111111111111110111100111100 +
b11111111111111111111001011000010 0
b11111111111111111111001011010001 @
b11010 )
1%
#310000
0%
#315000
b11111111111111111111100110111001 4
b11111111111111111110111100110101 3
b11111111111111111111010101111100 5
b1110111101000011 $
b1110111101000011 >
b11111111111111111110111101000011 ?
b11111111111111111110111100101101 +
b11111111111111111111001010110011 0
b11111111111111111111001011000010 @
b11100 &
b11100 A
b11011 )
1%
#320000
0%
#325000
b11111111111111111111100110110011 4
b11111111111111111110111100100101 3
b11111111111111111111010101110010 5
b11101 &
b11101 A
b1110111100110101 $
b1110111100110101 >
b11111111111111111110111100110101 ?
b11111111111111111110111100011110 +
b11111111111111111111001010100100 0
b11111111111111111111001010110011 @
b11100 )
1%
#330000
0%
#335000
b11111111111111111111100110101101 4
b11111111111111111110111100010110 3
b11111111111111111111010101101001 5
b1110111100100101 $
b1110111100100101 >
b11111111111111111110111100100101 ?
b11111111111111111110111100001111 +
b11111111111111111111001010010101 0
b11111111111111111111001010100100 @
b11110 &
b11110 A
b11101 )
1%
#340000
0%
#345000
b11111111111111111111100110101000 4
b11111111111111111110111100001000 3
b11111111111111111111010101100000 5
b11111 &
b11111 A
b1110111100010110 $
b1110111100010110 >
b11111111111111111110111100010110 ?
b11111111111111111110111100000000 +
b11111111111111111111001010000110 0
b11111111111111111111001010010101 @
b11110 )
1%
#350000
0%
#355000
b11111111111111111111100110100011 4
b11111111111111111110111011111001 3
b11111111111111111111010101010110 5
b1110111100001000 $
b1110111100001000 >
b11111111111111111110111100001000 ?
b11111111111111111110111011110001 +
b11111111111111111111001001110111 0
b11111111111111111111001010000110 @
b100000 &
b100000 A
b11111 )
1%
#360000
0%
#365000
b11111111111111111111100110011101 4
b11111111111111111110111011101010 3
b11111111111111111111010101001101 5
b100001 &
b100001 A
b1110111011111001 $
b1110111011111001 >
b11111111111111111110111011111001 ?
b11111111111111111110111011100010 +
b11111111111111111111001001101000 0
b11111111111111111111001001110111 @
b100000 )
1%
#370000
0%
#375000
b11111111111111111111100110010111 4
b11111111111111111110111011011010 3
b11111111111111111111010101000011 5
b1110111011101010 $
b1110111011101010 >
b11111111111111111110111011101010 ?
b11111111111111111110111011010011 +
b11111111111111111111001001011001 0
b11111111111111111111001001101000 @
b100010 &
b100010 A
b100001 )
1%
#380000
0%
#385000
b11111111111111111111100110010001 4
b11111111111111111110111011001011 3
b11111111111111111111010100111010 5
b100011 &
b100011 A
b1110111011011010 $
b1110111011011010 >
b11111111111111111110111011011010 ?
b11111111111111111110111011000100 +
b11111111111111111111001001001010 0
b11111111111111111111001001011001 @
b100010 )
1%
#390000
0%
#395000
b11111111111111111111100110001100 4
b11111111111111111110111010111101 3
b11111111111111111111010100110001 5
b1110111011001011 $
b1110111011001011 >
b11111111111111111110111011001011 ?
b11111111111111111110111010110101 +
b11111111111111111111001000111011 0
b11111111111111111111001001001010 @
b100100 &
b100100 A
b100011 )
1%
#400000
0%
#405000
b11111111111111111111100110000110 4
b11111111111111111110111010101101 3
b11111111111111111111010100100111 5
b100101 &
b100101 A
b1110111010111101 $
b1110111010111101 >
b11111111111111111110111010111101 ?
b11111111111111111110111010100110 +
b11111111111111111111001000101100 0
b11111111111111111111001000111011 @
b100100 )
1%
#410000
0%
#415000
b11111111111111111111100110000000 4
b11111111111111111110111010011110 3
b11111111111111111111010100011110 5
b1110111010101101 $
b1110111010101101 >
b11111111111111111110111010101101 ?
b11111111111111111110111010010111 +
b11111111111111111111001000011101 0
b11111111111111111111001000101100 @
b100110 &
b100110 A
b100101 )
1%
#420000
0%
#425000
b11111111111111111111100101111011 4
b11111111111111111110111010010000 3
b11111111111111111111010100010101 5
b100111 &
b100111 A
b1110111010011110 $
b1110111010011110 >
b11111111111111111110111010011110 ?
b11111111111111111110111010001000 +
b11111111111111111111001000001110 0
b11111111111111111111001000011101 @
b100110 )
1%
#430000
0%
#435000
b11111111111111111111100101110110 4
b11111111111111111110111010000001 3
b11111111111111111111010100001011 5
b1110111010010000 $
b1110111010010000 >
b11111111111111111110111010010000 ?
b11111111111111111110111001111001 +
b11111111111111111111000111111111 0
b11111111111111111111001000001110 @
b101000 &
b101000 A
b100111 )
1%
#440000
0%
#445000
b11111111111111111111100101110000 4
b11111111111111111110111001110010 3
b11111111111111111111010100000010 5
b101001 &
b101001 A
b1110111010000001 $
b1110111010000001 >
b11111111111111111110111010000001 ?
b11111111111111111110111001101010 +
b11111111111111111111000111110000 0
b11111111111111111111000111111111 @
b101000 )
1%
#450000
0%
#455000
b11111111111111111111100101101010 4
b11111111111111111110111001100010 3
b11111111111111111111010011111000 5
b1110111001110010 $
b1110111001110010 >
b11111111111111111110111001110010 ?
b11111111111111111110111001011011 +
b11111111111111111111000111100001 0
b11111111111111111111000111110000 @
b101010 &
b101010 A
b101001 )
1%
#460000
0%
#465000
b11111111111111111111100101100100 4
b11111111111111111110111001010011 3
b11111111111111111111010011101111 5
b101011 &
b101011 A
b1110111001100010 $
b1110111001100010 >
b11111111111111111110111001100010 ?
b11111111111111111110111001001100 +
b11111111111111111111000111010010 0
b11111111111111111111000111100001 @
b101010 )
1%
#470000
0%
#475000
b11111111111111111111100101011111 4
b11111111111111111110111001000101 3
b11111111111111111111010011100110 5
b1110111001010011 $
b1110111001010011 >
b11111111111111111110111001010011 ?
b11111111111111111110111000111101 +
b11111111111111111111000111000011 0
b11111111111111111111000111010010 @
b101100 &
b101100 A
b101011 )
1%
#480000
0%
#485000
b11111111111111111111100101011001 4
b11111111111111111110111000110101 3
b11111111111111111111010011011100 5
b101101 &
b101101 A
b1110111001000101 $
b1110111001000101 >
b11111111111111111110111001000101 ?
b11111111111111111110111000101110 +
b11111111111111111111000110110100 0
b11111111111111111111000111000011 @
b101100 )
1%
#490000
0%
#495000
b11111111111111111111100101010011 4
b11111111111111111110111000100110 3
b11111111111111111111010011010011 5
b1110111000110101 $
b1110111000110101 >
b11111111111111111110111000110101 ?
b11111111111111111110111000011111 +
b11111111111111111111000110100101 0
b11111111111111111111000110110100 @
b101110 &
b101110 A
b101101 )
1%
#500000
0%
#505000
b11111111111111111111100101001110 4
b11111111111111111110111000011000 3
b11111111111111111111010011001010 5
b101111 &
b101111 A
b1110111000100110 $
b1110111000100110 >
b11111111111111111110111000100110 ?
b11111111111111111110111000010000 +
b11111111111111111111000110010110 0
b11111111111111111111000110100101 @
b101110 )
1%
#510000
0%
#515000
b11111111111111111111100101001001 4
b11111111111111111110111000001001 3
b11111111111111111111010011000000 5
b1110111000011000 $
b1110111000011000 >
b11111111111111111110111000011000 ?
b11111111111111111110111000000001 +
b11111111111111111111000110000111 0
b11111111111111111111000110010110 @
b110000 &
b110000 A
b101111 )
1%
#520000
0%
#525000
b11111111111111111111100101000011 4
b11111111111111111110110111111010 3
b11111111111111111111010010110111 5
b110001 &
b110001 A
b1110111000001001 $
b1110111000001001 >
b11111111111111111110111000001001 ?
b11111111111111111110110111110010 +
b11111111111111111111000101111000 0
b11111111111111111111000110000111 @
b110000 )
1%
#530000
0%
#535000
b1 1
b100001110 ,
b11111111111111111111100100111101 4
b11111111111111111110111101111110 3
b11111111111111111111011001000001 5
b10101100111110000 2
b1000101001100 #
b1000101001100 /
b1000101001100 J
b1000011101100111101011000 -
b11011000101001011110 "
b11011000101001011110 .
b11011000101001011110 K
b1110110111111010 $
b1110110111111010 >
b11111111111111111110110111111010 ?
b11111111111111111111000001101001 +
b11111111111111111111000101110111 0
b11111111111111111111000101111000 @
b110010 &
b110010 A
b110001 )
1%
#540000
0%
#545000
b11111111111111111111000000010000 3
b11111111111111111111100111001111 4
b110011 &
b110011 A
b1110111101111110 $
b1110111101111110 >
b11111111111111111110111101111110 ?
b11111111111111111111000001101000 +
b11111111111111111111000101110110 0
b11111111111111111111000101110111 @
b0 )
1%
#550000
0%
#555000
b1000011 ,
b0 1
b11111111111111111111101000000110 4
b11111111111111111111000011000101 3
b11111111111111111111011010111111 5
b101 M
b1111000000010000 $
b1111000000010000 >
b11111111111111111111000000010000 ?
b11111111111111111111000100110011 +
b11111111111111111111000101110110 0
b11111111111111111111000101110110 @
b110100 &
b110100 A
b10000111011001111010110 -
b101011001111100 2
b101 '
b101 *
b101 L
b1 )
1%
#560000
0%
#565000
b11111111111111111111000100001000 3
b11111111111111111111101001001001 4
b110101 &
b110101 A
b1 P
b1111000011000101 $
b1111000011000101 >
b11111111111111111111000011000101 ?
b10 )
1%
#570000
0%
#575000
b11111111111111111111000100100010 3
b11111111111111111111101001100011 4
b1111000100001000 $
b1111000100001000 >
b11111111111111111111000100001000 ?
b10 P
b110110 &
b110110 A
b11 )
1%
#580000
0%
#585000
b11111111111111111111000100101011 3
b11111111111111111111101001101100 4
b110111 &
b110111 A
b11 P
b1111000100100010 $
b1111000100100010 >
b11111111111111111111000100100010 ?
b100 )
1%
#590000
0%
#595000
b11111111111111111111000100101111 3
b11111111111111111111101001110000 4
b1111000100101011 $
b1111000100101011 >
b11111111111111111111000100101011 ?
b100 P
b111000 &
b111000 A
b101 )
1%
#600000
0%
#605000
b11111111111111111111000100110000 3
b11111111111111111111101001110001 4
b111001 &
b111001 A
b101 P
b1111000100101111 $
b1111000100101111 >
b11111111111111111111000100101111 ?
b110 )
1%
#610000
0%
#615000
b11111111111111111111000100110001 3
b11111111111111111111101001110010 4
b1111000100110000 $
b1111000100110000 >
b11111111111111111111000100110000 ?
b110 P
b111010 &
b111010 A
b111 )
1%
#620000
0%
#625000
b111011 &
b111011 A
b111 P
b1111000100110001 $
b1111000100110001 >
b11111111111111111111000100110001 ?
b1000 )
1%
#630000
0%
#635000
b1000 P
b111100 &
b111100 A
b1001 )
1%
#640000
0%
#645000
b111101 &
b111101 A
b1001 P
b1010 )
1%
#650000
0%
#655000
b1010 P
b111110 &
b111110 A
b1011 )
1%
#660000
0%
#665000
b111111 &
b111111 A
b1011 P
b1100 )
1%
#670000
0%
#675000
b1100 P
b1000000 &
b1000000 A
b1101 )
1%
#680000
0%
#685000
b1000001 &
b1000001 A
b1101 P
b1110 )
1%
#690000
0%
#695000
b1110 P
b1000010 &
b1000010 A
b1111 )
1%
#700000
0%
#705000
b1000011 &
b1000011 A
b1111 P
b10000 )
1%
#710000
0%
#715000
b10000 P
b1000100 &
b1000100 A
b10001 )
1%
#720000
0%
#725000
b1000101 &
b1000101 A
b10001 P
b10010 )
1%
#730000
0%
#735000
b10010 P
b1000110 &
b1000110 A
b10011 )
1%
#740000
0%
#745000
b1000111 &
b1000111 A
b10011 P
b10100 )
1%
#750000
0%
#755000
b10100 P
b1001000 &
b1001000 A
b10101 )
1%
