CIC_Decimator/CIC_Decimator.v
`timescale 1ns/1ps

module cic_decimator(
    input clk,
    input reset,
    input signed [31:0] pd_out,
    input [15:0] counter,

    output reg do_update,
    output reg signed [31:0] current_phi_error
);

parameter DECIM = 4;

reg signed [63:0] acc1_reg;
reg signed [63:0] acc2_reg;

reg signed [63:0] acc2_z1;
reg signed [63:0] diff1_z1;

reg signed [63:0] diff1;
reg signed [63:0] diff2;

always @(posedge clk) begin

    if(reset) begin
        acc1_reg <= 0;
        acc2_reg <= 0;

        acc2_z1 <= 0;
        diff1_z1 <= 0;

        diff1 <= 0;
        diff2 <= 0;

        current_phi_error <= 0;
        do_update <= 0;
    end
    else begin

        acc1_reg <= acc1_reg + pd_out;
        acc2_reg <= acc2_reg + acc1_reg;

        do_update <= 0;

        if ((counter % DECIM) == (DECIM-1)) begin

            diff1 <= acc2_reg - acc2_z1;
            acc2_z1 <= acc2_reg;

            diff2 <= diff1 - diff1_z1;
            diff1_z1 <= diff1;

            current_phi_error <= diff2 >>> 4; // divide by 16

            do_update <= 1;
        end
    end
end

endmodule

CIC_Decimator/CIC_Decimator_tb.v
`timescale 1ns/1ps

module tb_cic_decimator;

    reg clk;
    reg reset;
    reg signed [31:0] pd_out;
    reg [15:0] counter;

    wire do_update;
    wire signed [31:0] current_phi_error;

    //----------------------------------------
    // DUT (Fixed module name instantiation)
    //----------------------------------------
    cic_decimator dut (
        .clk(clk),
        .reset(reset),
        .pd_out(pd_out),
        .counter(counter),
        .do_update(do_update),
        .current_phi_error(current_phi_error)
    );

    //----------------------------------------
    // Clock generation
    //----------------------------------------
    initial begin
        clk = 0;
        forever #5 clk = ~clk;   // 100 MHz
    end

    //----------------------------------------
    // Stimulus (Modified to capture 5 outputs)
    //----------------------------------------
    integer update_count = 0;

    initial begin
        $display("TESTBENCH STARTED");
        reset   = 1;
        pd_out  = 0;
        counter = 0;

        #50;
        @(posedge clk);
        reset = 0;

        // Provide a constant phase error input
        pd_out = 32'sd100; 

        // Keep running until we observe exactly 5 decimation outputs
        while (update_count < 5) begin
            @(posedge clk);
            counter <= counter + 1;
            
            if (do_update) begin
                update_count = update_count + 1;
            end
        end

        #20;
        $display("TESTBENCH FINISHED (Captured 5 outputs)");
        $finish;
    end

    //----------------------------------------
    // Monitor output
    //----------------------------------------
    always @(posedge clk) begin
        if(do_update) begin
            $display(
                "Output #%0d | Time=%0t | Counter=%0d | pd_out=%0d | phi_err=%0d",
                update_count + 1, // Lookahead index for display
                $time,
                counter,
                pd_out,
                current_phi_error
            );
        end
    end

    //----------------------------------------
    // Waveform Dump
    //----------------------------------------
    initial begin
        $dumpfile("cic.vcd");
        $dumpvars(0, tb_cic_decimator);
    end

endmodule

CIC_Decimator/cic.vcd
$date
	Wed Jun 17 19:00:11 2026
$end
$version
	Icarus Verilog
$end
$timescale
	1ps
$end
$scope module tb_cic_decimator $end
$var wire 1 ! do_update $end
$var wire 32 " current_phi_error [31:0] $end
$var reg 1 # clk $end
$var reg 16 $ counter [15:0] $end
$var reg 32 % pd_out [31:0] $end
$var reg 1 & reset $end
$var integer 32 ' update_count [31:0] $end
$scope module dut $end
$var wire 1 # clk $end
$var wire 16 ( counter [15:0] $end
$var wire 32 ) pd_out [31:0] $end
$var wire 1 & reset $end
$var parameter 32 * DECIM $end
$var reg 64 + acc1_reg [63:0] $end
$var reg 64 , acc2_reg [63:0] $end
$var reg 64 - acc2_z1 [63:0] $end
$var reg 32 . current_phi_error [31:0] $end
$var reg 64 / diff1 [63:0] $end
$var reg 64 0 diff1_z1 [63:0] $end
$var reg 64 1 diff2 [63:0] $end
$var reg 1 ! do_update $end
$upscope $end
$upscope $end
$enddefinitions $end
$comment Show the parameter values. $end
$dumpall
b100 *
$end
#0
$dumpvars
bx 1
bx 0
bx /
bx .
bx -
bx ,
bx +
b0 )
b0 (
b0 '
1&
b0 %
b0 $
0#
bx "
x!
$end
#5000
0!
b0 "
b0 .
b0 1
b0 /
b0 0
b0 -
b0 ,
b0 +
1#
#10000
0#
#15000
1#
#20000
0#
#25000
1#
#30000
0#
#35000
1#
#40000
0#
#45000
1#
#50000
0#
#55000
b1100100 +
b1100100 %
b1100100 )
0&
1#
#60000
0#
#65000
b1 $
b1 (
b1100100 ,
b11001000 +
1#
#70000
0#
#75000
b100101100 ,
b100101100 +
b10 $
b10 (
1#
#80000
0#
#85000
b11 $
b11 (
b1001011000 ,
b110010000 +
1#
#90000
0#
#95000
1!
b1001011000 -
b1001011000 /
b1111101000 ,
b111110100 +
b100 $
b100 (
1#
#100000
0#
#105000
b101 $
b101 (
0!
b10111011100 ,
b1001011000 +
b1 '
1#
#110000
0#
#115000
b100000110100 ,
b1010111100 +
b110 $
b110 (
1#
#120000
0#
#125000
b111 $
b111 (
b101011110000 ,
b1100100000 +
1#
#130000
0#
#135000
1!
b1001011000 0
b1001011000 1
b101011110000 -
b100010011000 /
b111000010000 ,
b1110000100 +
b1000 $
b1000 (
1#
#140000
0#
#145000
b1001 $
b1001 (
0!
b1000110010100 ,
b1111101000 +
b10 '
1#
#150000
0#
#155000
b1010101111100 ,
b10001001100 +
b1010 $
b1010 (
1#
#160000
0#
#165000
b1011 $
b1011 (
b1100111001000 ,
b10010110000 +
1#
#170000
0#
#175000
1!
b100101 "
b100101 .
b100010011000 0
b11001000000 1
b1100111001000 -
b111011011000 /
b1111001111000 ,
b10100010100 +
b1100 $
b1100 (
1#
#180000
0#
#185000
b1101 $
b1101 (
0!
b10001110001100 ,
b10101111000 +
b11 '
1#
#190000
0#
#195000
b10100100000100 ,
b10111011100 +
b1110 $
b1110 (
1#
#200000
0#
#205000
b1111 $
b1111 (
b10111011100000 ,
b11001000000 +
1#
#210000
0#
#215000
1!
b1100100 "
b1100100 .
b111011011000 0
b10111011100000 -
b1010100011000 /
b11010100100000 ,
b11010100100 +
b10000 $
b10000 (
1#
#220000
0#
#225000
b10001 $
b10001 (
0!
b11101111000100 ,
b11100001000 +
b100 '
1#
#230000
0#
#235000
b100001011001100 ,
b11101101100 +
b10010 $
b10010 (
1#
#240000
0#
#245000
b10011 $
b10011 (
b100101000111000 ,
b11111010000 +
1#
#250000
0#
#255000
1!
b1010100011000 0
b100101000111000 -
b1101101011000 /
b101001000001000 ,
b100000110100 +
b10100 $
b10100 (
1#
#260000
0#
#265000
b10101 $
b10101 (
0!
b101101000111100 ,
b100010011000 +
b101 '
1#
#270000
0#
#275000
b110001011010100 ,
b100011111100 +
1#
#280000
0#
#285000
b110101111010000 ,
b100101100000 +
1#
