ADPLL_Integrated5/mash_modulator.v
module mash_modulator(
    input [6:0]F_mod,
    input [6:0]K_mod,
    input [4:0]N_int,
    input clk,
    input rst,
    output reg [4:0]N_div,
    output reg [6:0]m1_reg,
    output reg c2_prev
);

reg [6:0]m2_reg;
reg c1, c2;
reg signed [2:0]sdm_out;

reg [7:0]m1_sum;
reg [7:0]m2_sum;
reg [4:0]ndiv_next;

always@ (*) begin
    c1 = 1'b0;
    c2 = 1'b0;
    sdm_out = 3'sd0;
    m1_sum = {1'b0, m1_reg} + {1'b0, K_mod};
    m2_sum = {1'b0, m2_reg} + {1'b0, m1_reg};
    ndiv_next = N_int;

    if(F_mod != {7{1'b0}}) begin
        if(m1_sum >= {1'b0,F_mod})
            c1 = 1'b1;

        m2_sum = {1'b0,m2_reg} + c1;
        if(m2_sum >= {1'b0,F_mod})
            c2 = 1'b1;

        sdm_out = (c1? 3'sd1:3'sd0) + (c2? 3'sd1:3'sd0) - (c2_prev? 3'sd1:3'sd0);

        if(sdm_out == -3'sd1)
            ndiv_next = ((N_int == 0) ? {5{1'b0}} : (N_int - 1'b1));
        else if(sdm_out == 3'sd1)
            ndiv_next = N_int + 1'b1;
        else if(sdm_out == 3'sd2)
            ndiv_next = N_int + 2'b10;
        else 
            ndiv_next = (N_int == 0) ? {5{1'b0}}:N_int;

    end
end


always@ (posedge clk or posedge rst) begin
    if(rst) begin
        m1_reg <= {7{1'b0}};
        m2_reg <= {7{1'b0}};
        c2_prev <= 1'b0;
        N_div <= {5{1'b0}};
    end
    else begin
        if(F_mod != {7{1'b0}}) begin
            if(m1_sum >= {1'b0,F_mod})
                m1_reg <= m1_sum - {1'b0,F_mod};
            else
                m1_reg <= m1_sum[6:0];

            if(m2_sum >= {1'b0,F_mod})
                m2_reg <= m2_sum - {1'b0,F_mod};
            else
                m2_reg <= m2_sum[6:0];

            c2_prev <= c2;
            N_div <= ndiv_next;
        end
        else begin
            m1_reg <= {7{1'b0}};
            m2_reg <= {7{1'b0}};
            c2_prev <= 1'b0;
            N_div <= N_int;
        end
    end
end

endmodule

MASH Modulator/tb_mash_modulator.v
`timescale 1ns/1ps

module tb_mash_modulator;
    reg clk;
    reg rst;
    reg [6:0]F_mod;
    reg [6:0]K_mod;
    reg [4:0]N_int;

    wire [4:0]N_div;
    wire [6:0]m1_reg;

    mash_modulator dut(.clk(clk), .rst(rst), .F_mod(F_mod), .K_mod(K_mod), .N_int(N_int), .N_div(N_div), .m1_reg(m1_reg));

    initial clk = 1'b0;
    always #5 clk = ~clk;

    initial begin 
        rst = 1'b1;
        F_mod = 7'd10;
        K_mod = 7'd1;
        N_int = 5'd8;

        #20
        rst = 1'b0;

        #3000

        $finish;
    end

    initial begin
        $monitor("t=%0t rst=%b F_mod=%0d K_mod=%0d N_int=%0d | N_div=%0d m1_reg=%0d",
                 $time, rst, F_mod, K_mod, N_int, N_div, m1_reg);
    end

    initial begin 
        $dumpfile("test.vcd");
        $dumpvars(0,dut);
    end

endmodule

MASH Modulator/test.vcd
$date
	Thu Jun 18 23:49:58 2026
$end
$version
	Icarus Verilog
$end
$timescale
	1ps
$end
$scope module tb_mash_modulator $end
$scope module dut $end
$var wire 7 ! F_mod [6:0] $end
$var wire 7 " K_mod [6:0] $end
$var wire 5 # N_int [4:0] $end
$var wire 1 $ clk $end
$var wire 1 % rst $end
$var reg 5 & N_div [4:0] $end
$var reg 1 ' c1 $end
$var reg 1 ( c2 $end
$var reg 1 ) c2_prev $end
$var reg 7 * m1_reg [6:0] $end
$var reg 8 + m1_sum [7:0] $end
$var reg 7 , m2_reg [6:0] $end
$var reg 8 - m2_sum [7:0] $end
$var reg 5 . ndiv_next [4:0] $end
$var reg 3 / sdm_out [2:0] $end
$upscope $end
$upscope $end
$enddefinitions $end
#0
$dumpvars
b0 /
b1000 .
b0 -
b0 ,
b1 +
b0 *
0)
0(
0'
b0 &
1%
0$
b1000 #
b1 "
b1010 !
$end
#5000
1$
#10000
0$
#15000
1$
#20000
0$
0%
#25000
b10 +
b1000 &
b1 *
1$
#30000
0$
#35000
b11 +
b10 *
1$
#40000
0$
#45000
b100 +
b11 *
1$
#50000
0$
#55000
b101 +
b100 *
1$
#60000
0$
#65000
b110 +
b101 *
1$
#70000
0$
#75000
b111 +
b110 *
1$
#80000
0$
#85000
b1000 +
b111 *
1$
#90000
0$
#95000
b1001 +
b1000 *
1$
#100000
0$
#105000
b1001 .
b1 /
b1 -
1'
b1010 +
b1001 *
1$
#110000
0$
#115000
b1000 .
b1 +
b0 /
0'
b1001 &
b1 ,
b0 *
1$
#120000
0$
#125000
b10 +
b1000 &
b1 *
1$
#130000
0$
#135000
b11 +
b10 *
1$
#140000
0$
#145000
b100 +
b11 *
1$
#150000
0$
#155000
b101 +
b100 *
1$
#160000
0$
#165000
b110 +
b101 *
1$
#170000
0$
#175000
b111 +
b110 *
1$
#180000
0$
#185000
b1000 +
b111 *
1$
#190000
0$
#195000
b1001 +
b1000 *
1$
#200000
0$
#205000
b1001 .
b1 /
b10 -
1'
b1010 +
b1001 *
1$
#210000
0$
#215000
b1000 .
b1 +
b0 /
0'
b1001 &
b10 ,
b0 *
1$
#220000
0$
#225000
b10 +
b1000 &
b1 *
1$
#230000
0$
#235000
b11 +
b10 *
1$
#240000
0$
#245000
b100 +
b11 *
1$
#250000
0$
#255000
b101 +
b100 *
1$
#260000
0$
#265000
b110 +
b101 *
1$
#270000
0$
#275000
b111 +
b110 *
1$
#280000
0$
#285000
b1000 +
b111 *
1$
#290000
0$
#295000
b1001 +
b1000 *
1$
#300000
0$
#305000
b1001 .
b1 /
b11 -
1'
b1010 +
b1001 *
1$
#310000
0$
#315000
b1000 .
b1 +
b0 /
0'
b1001 &
b11 ,
b0 *
1$
#320000
0$
#325000
b10 +
b1000 &
b1 *
1$
#330000
0$
#335000
b11 +
b10 *
1$
#340000
0$
#345000
b100 +
b11 *
1$
#350000
0$
#355000
b101 +
b100 *
1$
#360000
0$
#365000
b110 +
b101 *
1$
#370000
0$
#375000
b111 +
b110 *
1$
#380000
0$
#385000
b1000 +
b111 *
1$
#390000
0$
#395000
b1001 +
b1000 *
1$
#400000
0$
#405000
b1001 .
b1 /
b100 -
1'
b1010 +
b1001 *
1$
#410000
0$
#415000
b1000 .
b1 +
b0 /
0'
b1001 &
b100 ,
b0 *
1$
#420000
0$
#425000
b10 +
b1000 &
b1 *
1$
#430000
0$
#435000
b11 +
b10 *
1$
#440000
0$
#445000
b100 +
b11 *
1$
#450000
0$
#455000
b101 +
b100 *
1$
#460000
0$
#465000
b110 +
b101 *
1$
#470000
0$
#475000
b111 +
b110 *
1$
#480000
0$
#485000
b1000 +
b111 *
1$
#490000
0$
#495000
b1001 +
b1000 *
1$
#500000
0$
#505000
b1001 .
b1 /
b101 -
1'
b1010 +
b1001 *
1$
#510000
0$
#515000
b1000 .
b1 +
b0 /
0'
b1001 &
b101 ,
b0 *
1$
#520000
0$
#525000
b10 +
b1000 &
b1 *
1$
#530000
0$
#535000
b11 +
b10 *
1$
#540000
0$
#545000
b100 +
b11 *
1$
#550000
0$
#555000
b101 +
b100 *
1$
#560000
0$
#565000
b110 +
b101 *
1$
#570000
0$
#575000
b111 +
b110 *
1$
#580000
0$
#585000
b1000 +
b111 *
1$
#590000
0$
#595000
b1001 +
b1000 *
1$
#600000
0$
#605000
b1001 .
b1 /
b110 -
1'
b1010 +
b1001 *
1$
#610000
0$
#615000
b1000 .
b1 +
b0 /
0'
b1001 &
b110 ,
b0 *
1$
#620000
0$
#625000
b10 +
b1000 &
b1 *
1$
#630000
0$
#635000
b11 +
b10 *
1$
#640000
0$
#645000
b100 +
b11 *
1$
#650000
0$
#655000
b101 +
b100 *
1$
#660000
0$
#665000
b110 +
b101 *
1$
#670000
0$
#675000
b111 +
b110 *
1$
#680000
0$
#685000
b1000 +
b111 *
1$
#690000
0$
#695000
b1001 +
b1000 *
1$
#700000
0$
#705000
b1001 .
b1 /
b111 -
1'
b1010 +
b1001 *
1$
#710000
0$
#715000
b1000 .
b1 +
b0 /
0'
b1001 &
b111 ,
b0 *
1$
#720000
0$
#725000
b10 +
b1000 &
b1 *
1$
#730000
0$
#735000
b11 +
b10 *
1$
#740000
0$
#745000
b100 +
b11 *
1$
#750000
0$
#755000
b101 +
b100 *
1$
#760000
0$
#765000
b110 +
b101 *
1$
#770000
0$
#775000
b111 +
b110 *
1$
#780000
0$
#785000
b1000 +
b111 *
1$
#790000
0$
#795000
b1001 +
b1000 *
1$
#800000
0$
#805000
b1001 .
b1 /
b1000 -
1'
b1010 +
b1001 *
1$
#810000
0$
#815000
b1000 .
b1 +
b0 /
0'
b1001 &
b1000 ,
b0 *
1$
#820000
0$
#825000
b10 +
b1000 &
b1 *
1$
#830000
0$
#835000
b11 +
b10 *
1$
#840000
0$
#845000
b100 +
b11 *
1$
#850000
0$
#855000
b101 +
b100 *
1$
#860000
0$
#865000
b110 +
b101 *
1$
#870000
0$
#875000
b111 +
b110 *
1$
#880000
0$
#885000
b1000 +
b111 *
1$
#890000
0$
#895000
b1001 +
b1000 *
1$
#900000
0$
#905000
b1001 .
b1 /
b1001 -
1'
b1010 +
b1001 *
1$
#910000
0$
#915000
b1000 .
b1 +
b0 /
0'
b1001 &
b1001 ,
b0 *
1$
#920000
0$
#925000
b10 +
b1000 &
b1 *
1$
#930000
0$
#935000
b11 +
b10 *
1$
#940000
0$
#945000
b100 +
b11 *
1$
#950000
0$
#955000
b101 +
b100 *
1$
#960000
0$
#965000
b110 +
b101 *
1$
#970000
0$
#975000
b111 +
b110 *
1$
#980000
0$
#985000
b1000 +
b111 *
1$
#990000
0$
#995000
b1001 +
b1000 *
1$
#1000000
0$
#1005000
b1010 .
b10 /
1(
b1010 -
1'
b1010 +
b1001 *
1$
#1010000
0$
#1015000
b111 .
b0 -
b1 +
b111 /
0(
0'
b1010 &
1)
b0 ,
b0 *
1$
#1020000
0$
#1025000
b1000 .
b10 +
b0 /
b111 &
0)
b1 *
1$
#1030000
0$
#1035000
b11 +
b1000 &
b10 *
1$
#1040000
0$
#1045000
b100 +
b11 *
1$
#1050000
0$
#1055000
b101 +
b100 *
1$
#1060000
0$
#1065000
b110 +
b101 *
1$
#1070000
0$
#1075000
b111 +
b110 *
1$
#1080000
0$
#1085000
b1000 +
b111 *
1$
#1090000
0$
#1095000
b1001 +
b1000 *
1$
#1100000
0$
#1105000
b1001 .
b1 /
b1 -
1'
b1010 +
b1001 *
1$
#1110000
0$
#1115000
b1000 .
b1 +
b0 /
0'
b1001 &
b1 ,
b0 *
1$
#1120000
0$
#1125000
b10 +
b1000 &
b1 *
1$
#1130000
0$
#1135000
b11 +
b10 *
1$
#1140000
0$
#1145000
b100 +
b11 *
1$
#1150000
0$
#1155000
b101 +
b100 *
1$
#1160000
0$
#1165000
b110 +
b101 *
1$
#1170000
0$
#1175000
b111 +
b110 *
1$
#1180000
0$
#1185000
b1000 +
b111 *
1$
#1190000
0$
#1195000
b1001 +
b1000 *
1$
#1200000
0$
#1205000
b1001 .
b1 /
b10 -
1'
b1010 +
b1001 *
1$
#1210000
0$
#1215000
b1000 .
b1 +
b0 /
0'
b1001 &
b10 ,
b0 *
1$
#1220000
0$
#1225000
b10 +
b1000 &
b1 *
1$
#1230000
0$
#1235000
b11 +
b10 *
1$
#1240000
0$
#1245000
b100 +
b11 *
1$
#1250000
0$
#1255000
b101 +
b100 *
1$
#1260000
0$
#1265000
b110 +
b101 *
1$
#1270000
0$
#1275000
b111 +
b110 *
1$
#1280000
0$
#1285000
b1000 +
b111 *
1$
#1290000
0$
#1295000
b1001 +
b1000 *
1$
#1300000
0$
#1305000
b1001 .
b1 /
b11 -
1'
b1010 +
b1001 *
1$
#1310000
0$
#1315000
b1000 .
b1 +
b0 /
0'
b1001 &
b11 ,
b0 *
1$
#1320000
0$
#1325000
b10 +
b1000 &
b1 *
1$
#1330000
0$
#1335000
b11 +
b10 *
1$
#1340000
0$
#1345000
b100 +
b11 *
1$
#1350000
0$
#1355000
b101 +
b100 *
1$
#1360000
0$
#1365000
b110 +
b101 *
1$
#1370000
0$
#1375000
b111 +
b110 *
1$
#1380000
0$
#1385000
b1000 +
b111 *
1$
#1390000
0$
#1395000
b1001 +
b1000 *
1$
#1400000
0$
#1405000
b1001 .
b1 /
b100 -
1'
b1010 +
b1001 *
1$
#1410000
0$
#1415000
b1000 .
b1 +
b0 /
0'
b1001 &
b100 ,
b0 *
1$
#1420000
0$
#1425000
b10 +
b1000 &
b1 *
1$
#1430000
0$
#1435000
b11 +
b10 *
1$
#1440000
0$
#1445000
b100 +
b11 *
1$
#1450000
0$
#1455000
b101 +
b100 *
1$
#1460000
0$
#1465000
b110 +
b101 *
1$
#1470000
0$
#1475000
b111 +
b110 *
1$
#1480000
0$
#1485000
b1000 +
b111 *
1$
#1490000
0$
#1495000
b1001 +
b1000 *
1$
#1500000
0$
#1505000
b1001 .
b1 /
b101 -
1'
b1010 +
b1001 *
1$
#1510000
0$
#1515000
b1000 .
b1 +
b0 /
0'
b1001 &
b101 ,
b0 *
1$
#1520000
0$
#1525000
b10 +
b1000 &
b1 *
1$
#1530000
0$
#1535000
b11 +
b10 *
1$
#1540000
0$
#1545000
b100 +
b11 *
1$
#1550000
0$
#1555000
b101 +
b100 *
1$
#1560000
0$
#1565000
b110 +
b101 *
1$
#1570000
0$
#1575000
b111 +
b110 *
1$
#1580000
0$
#1585000
b1000 +
b111 *
1$
#1590000
0$
#1595000
b1001 +
b1000 *
1$
#1600000
0$
#1605000
b1001 .
b1 /
b110 -
1'
b1010 +
b1001 *
1$
#1610000
0$
#1615000
b1000 .
b1 +
b0 /
0'
b1001 &
b110 ,
b0 *
1$
#1620000
0$
#1625000
b10 +
b1000 &
b1 *
1$
#1630000
0$
#1635000
b11 +
b10 *
1$
#1640000
0$
#1645000
b100 +
b11 *
1$
#1650000
0$
#1655000
b101 +
b100 *
1$
#1660000
0$
#1665000
b110 +
b101 *
1$
#1670000
0$
#1675000
b111 +
b110 *
1$
#1680000
0$
#1685000
b1000 +
b111 *
1$
#1690000
0$
#1695000
b1001 +
b1000 *
1$
#1700000
0$
#1705000
b1001 .
b1 /
b111 -
1'
b1010 +
b1001 *
1$
#1710000
0$
#1715000
b1000 .
b1 +
b0 /
0'
b1001 &
b111 ,
b0 *
1$
#1720000
0$
#1725000
b10 +
b1000 &
b1 *
1$
#1730000
0$
#1735000
b11 +
b10 *
1$
#1740000
0$
#1745000
b100 +
b11 *
1$
#1750000
0$
#1755000
b101 +
b100 *
1$
#1760000
0$
#1765000
b110 +
b101 *
1$
#1770000
0$
#1775000
b111 +
b110 *
1$
#1780000
0$
#1785000
b1000 +
b111 *
1$
#1790000
0$
#1795000
b1001 +
b1000 *
1$
#1800000
0$
#1805000
b1001 .
b1 /
b1000 -
1'
b1010 +
b1001 *
1$
#1810000
0$
#1815000
b1000 .
b1 +
b0 /
0'
b1001 &
b1000 ,
b0 *
1$
#1820000
0$
#1825000
b10 +
b1000 &
b1 *
1$
#1830000
0$
#1835000
b11 +
b10 *
1$
#1840000
0$
#1845000
b100 +
b11 *
1$
#1850000
0$
#1855000
b101 +
b100 *
1$
#1860000
0$
#1865000
b110 +
b101 *
1$
#1870000
0$
#1875000
b111 +
b110 *
1$
#1880000
0$
#1885000
b1000 +
b111 *
1$
#1890000
0$
#1895000
b1001 +
b1000 *
1$
#1900000
0$
#1905000
b1001 .
b1 /
b1001 -
1'
b1010 +
b1001 *
1$
#1910000
0$
#1915000
b1000 .
b1 +
b0 /
0'
b1001 &
b1001 ,
b0 *
1$
#1920000
0$
#1925000
b10 +
b1000 &
b1 *
1$
#1930000
0$
#1935000
b11 +
b10 *
1$
#1940000
0$
#1945000
b100 +
b11 *
1$
#1950000
0$
#1955000
b101 +
b100 *
1$
#1960000
0$
#1965000
b110 +
b101 *
1$
#1970000
0$
#1975000
b111 +
b110 *
1$
#1980000
0$
#1985000
b1000 +
b111 *
1$
#1990000
0$
#1995000
b1001 +
b1000 *
1$
#2000000
0$
#2005000
b1010 .
b10 /
1(
b1010 -
1'
b1010 +
b1001 *
1$
#2010000
0$
#2015000
b111 .
b0 -
b1 +
b111 /
0(
0'
b1010 &
1)
b0 ,
b0 *
1$
#2020000
0$
#2025000
b1000 .
b10 +
b0 /
b111 &
0)
b1 *
1$
#2030000
0$
#2035000
b11 +
b1000 &
b10 *
1$
#2040000
0$
#2045000
b100 +
b11 *
1$
#2050000
0$
#2055000
b101 +
b100 *
1$
#2060000
0$
#2065000
b110 +
b101 *
1$
#2070000
0$
#2075000
b111 +
b110 *
1$
#2080000
0$
#2085000
b1000 +
b111 *
1$
#2090000
0$
#2095000
b1001 +
b1000 *
1$
#2100000
0$
#2105000
b1001 .
b1 /
b1 -
1'
b1010 +
b1001 *
1$
#2110000
0$
#2115000
b1000 .
b1 +
b0 /
0'
b1001 &
b1 ,
b0 *
1$
#2120000
0$
#2125000
b10 +
b1000 &
b1 *
1$
#2130000
0$
#2135000
b11 +
b10 *
1$
#2140000
0$
#2145000
b100 +
b11 *
1$
#2150000
0$
#2155000
b101 +
b100 *
1$
#2160000
0$
#2165000
b110 +
b101 *
1$
#2170000
0$
#2175000
b111 +
b110 *
1$
#2180000
0$
#2185000
b1000 +
b111 *
1$
#2190000
0$
#2195000
b1001 +
b1000 *
1$
#2200000
0$
#2205000
b1001 .
b1 /
b10 -
1'
b1010 +
b1001 *
1$
#2210000
0$
#2215000
b1000 .
b1 +
b0 /
0'
b1001 &
b10 ,
b0 *
1$
#2220000
0$
#2225000
b10 +
b1000 &
b1 *
1$
#2230000
0$
#2235000
b11 +
b10 *
1$
#2240000
0$
#2245000
b100 +
b11 *
1$
#2250000
0$
#2255000
b101 +
b100 *
1$
#2260000
0$
#2265000
b110 +
b101 *
1$
#2270000
0$
#2275000
b111 +
b110 *
1$
#2280000
0$
#2285000
b1000 +
b111 *
1$
#2290000
0$
#2295000
b1001 +
b1000 *
1$
#2300000
0$
#2305000
b1001 .
b1 /
b11 -
1'
b1010 +
b1001 *
1$
#2310000
0$
#2315000
b1000 .
b1 +
b0 /
0'
b1001 &
b11 ,
b0 *
1$
#2320000
0$
#2325000
b10 +
b1000 &
b1 *
1$
#2330000
0$
#2335000
b11 +
b10 *
1$
#2340000
0$
#2345000
b100 +
b11 *
1$
#2350000
0$
#2355000
b101 +
b100 *
1$
#2360000
0$
#2365000
b110 +
b101 *
1$
#2370000
0$
#2375000
b111 +
b110 *
1$
#2380000
0$
#2385000
b1000 +
b111 *
1$
#2390000
0$
#2395000
b1001 +
b1000 *
1$
#2400000
0$
#2405000
b1001 .
b1 /
b100 -
1'
b1010 +
b1001 *
1$
#2410000
0$
#2415000
b1000 .
b1 +
b0 /
0'
b1001 &
b100 ,
b0 *
1$
#2420000
0$
#2425000
b10 +
b1000 &
b1 *
1$
#2430000
0$
#2435000
b11 +
b10 *
1$
#2440000
0$
#2445000
b100 +
b11 *
1$
#2450000
0$
#2455000
b101 +
b100 *
1$
#2460000
0$
#2465000
b110 +
b101 *
1$
#2470000
0$
#2475000
b111 +
b110 *
1$
#2480000
0$
#2485000
b1000 +
b111 *
1$
#2490000
0$
#2495000
b1001 +
b1000 *
1$
#2500000
0$
#2505000
b1001 .
b1 /
b101 -
1'
b1010 +
b1001 *
1$
#2510000
0$
#2515000
b1000 .
b1 +
b0 /
0'
b1001 &
b101 ,
b0 *
1$
#2520000
0$
#2525000
b10 +
b1000 &
b1 *
1$
#2530000
0$
#2535000
b11 +
b10 *
1$
#2540000
0$
#2545000
b100 +
b11 *
1$
#2550000
0$
#2555000
b101 +
b100 *
1$
#2560000
0$
#2565000
b110 +
b101 *
1$
#2570000
0$
#2575000
b111 +
b110 *
1$
#2580000
0$
#2585000
b1000 +
b111 *
1$
#2590000
0$
#2595000
b1001 +
b1000 *
1$
#2600000
0$
#2605000
b1001 .
b1 /
b110 -
1'
b1010 +
b1001 *
1$
#2610000
0$
#2615000
b1000 .
b1 +
b0 /
0'
b1001 &
b110 ,
b0 *
1$
#2620000
0$
#2625000
b10 +
b1000 &
b1 *
1$
#2630000
0$
#2635000
b11 +
b10 *
1$
#2640000
0$
#2645000
b100 +
b11 *
1$
#2650000
0$
#2655000
b101 +
b100 *
1$
#2660000
0$
#2665000
b110 +
b101 *
1$
#2670000
0$
#2675000
b111 +
b110 *
1$
#2680000
0$
#2685000
b1000 +
b111 *
1$
#2690000
0$
#2695000
b1001 +
b1000 *
1$
#2700000
0$
#2705000
b1001 .
b1 /
b111 -
1'
b1010 +
b1001 *
1$
#2710000
0$
#2715000
b1000 .
b1 +
b0 /
0'
b1001 &
b111 ,
b0 *
1$
#2720000
0$
#2725000
b10 +
b1000 &
b1 *
1$
#2730000
0$
#2735000
b11 +
b10 *
1$
#2740000
0$
#2745000
b100 +
b11 *
1$
#2750000
0$
#2755000
b101 +
b100 *
1$
#2760000
0$
#2765000
b110 +
b101 *
1$
#2770000
0$
#2775000
b111 +
b110 *
1$
#2780000
0$
#2785000
b1000 +
b111 *
1$
#2790000
0$
#2795000
b1001 +
b1000 *
1$
#2800000
0$
#2805000
b1001 .
b1 /
b1000 -
1'
b1010 +
b1001 *
1$
#2810000
0$
#2815000
b1000 .
b1 +
b0 /
0'
b1001 &
b1000 ,
b0 *
1$
#2820000
0$
#2825000
b10 +
b1000 &
b1 *
1$
#2830000
0$
#2835000
b11 +
b10 *
1$
#2840000
0$
#2845000
b100 +
b11 *
1$
#2850000
0$
#2855000
b101 +
b100 *
1$
#2860000
0$
#2865000
b110 +
b101 *
1$
#2870000
0$
#2875000
b111 +
b110 *
1$
#2880000
0$
#2885000
b1000 +
b111 *
1$
#2890000
0$
#2895000
b1001 +
b1000 *
1$
#2900000
0$
#2905000
b1001 .
b1 /
b1001 -
1'
b1010 +
b1001 *
1$
#2910000
0$
#2915000
b1000 .
b1 +
b0 /
0'
b1001 &
b1001 ,
b0 *
1$
#2920000
0$
#2925000
b10 +
b1000 &
b1 *
1$
#2930000
0$
#2935000
b11 +
b10 *
1$
#2940000
0$
#2945000
b100 +
b11 *
1$
#2950000
0$
#2955000
b101 +
b100 *
1$
#2960000
0$
#2965000
b110 +
b101 *
1$
#2970000
0$
#2975000
b111 +
b110 *
1$
#2980000
0$
#2985000
b1000 +
b111 *
1$
#2990000
0$
#2995000
b1001 +
b1000 *
1$
#3000000
0$
#3005000
b1010 .
b10 /
1(
b1010 -
1'
b1010 +
b1001 *
1$
#3010000
0$
#3015000
b111 .
b0 -
b1 +
b111 /
0(
0'
b1010 &
1)
b0 ,
b0 *
1$
