ADPLL_scaled_v4/phase_detector.v
module phase_detector(
    input ref_clk,
    input fb_clk,
    input rst,
    output reg signed [24:0]phase_error
);

reg [23:0] phase_ref;

//Reference phase accumulator
always@(posedge ref_clk or posedge rst) begin
    if(rst)
        phase_ref <= 24'd0;
    else 
        phase_ref <= phase_ref + 24'd1;
end

//Feedback phase accumulator
reg[23:0] phase_fb_bin;
always@(posedge fb_clk or posedge rst) begin
    if(rst)
        phase_fb_bin <= 24'd0;
    else 
        phase_fb_bin <= phase_fb_bin + 24'd1;
end

//Binary to gray code
wire [23:0]phase_fb_gray;
assign phase_fb_gray = (phase_fb_bin) ^ (phase_fb_bin >> 1);

//2-FF synchronizer
reg [23:0]gray_sync1;
reg [23:0]gray_sync2;

always@(posedge ref_clk or posedge rst) begin
    if(rst) begin
        gray_sync1 <= 24'd0;
        gray_sync2 <= 24'd0;
    end
    else begin
        gray_sync1 <= phase_fb_gray;
        gray_sync2 <= gray_sync1;
    end
end

//Gray to Binary
wire [23:0]phase_fb_bin_sync;
genvar i;
generate 
    assign phase_fb_bin_sync[23] = gray_sync2[23];
    for(i = 22; i>=0; i=i-1)
        assign phase_fb_bin_sync[i] = phase_fb_bin_sync[i+1] ^ gray_sync2[i];
endgenerate

//Phase error calculation
always@(posedge ref_clk or posedge rst) begin
    if(rst)
        phase_error <= 25'sd0;
    else
        phase_error <= $signed({1'b0,phase_ref}) - $signed({1'b0,phase_fb_bin_sync});
end

endmodule

Phase Detector/tb_phase_detector.v
`timescale 1ns/1ps

module tb_phase_detector();

reg ref_clk;
reg fb_clk;
reg rst;

wire signed [24:0]phase_error;

phase_detector dut(.ref_clk(ref_clk), .fb_clk(fb_clk), .rst(rst), .phase_error(phase_error));

initial ref_clk = 1'b0;
always #5 ref_clk = ~ref_clk;

initial fb_clk = 1'b0;
always #3.5 fb_clk = ~fb_clk;

initial begin
    rst = 1'b1;
    #20
    rst = 1'b0;

    #2000

    $finish;
end

initial begin
    $monitor("t=%0t rst=%b phase_error=%0d", $time, rst, phase_error);
end

initial begin
    $dumpfile("test.vcd");
    $dumpvars(0,dut);
end


endmodule

Phase Detector/test.vcd
$date
	Fri Jun 19 21:22:40 2026
$end
$version
	Icarus Verilog
$end
$timescale
	1ps
$end
$scope module tb_phase_detector $end
$scope module dut $end
$var wire 1 ! fb_clk $end
$var wire 24 " phase_fb_gray [23:0] $end
$var wire 1 # ref_clk $end
$var wire 1 $ rst $end
$var wire 24 % phase_fb_bin_sync [23:0] $end
$var reg 24 & gray_sync1 [23:0] $end
$var reg 24 ' gray_sync2 [23:0] $end
$var reg 25 ( phase_error [24:0] $end
$var reg 24 ) phase_fb_bin [23:0] $end
$var reg 24 * phase_ref [23:0] $end
$scope begin genblk1[0] $end
$upscope $end
$scope begin genblk1[1] $end
$upscope $end
$scope begin genblk1[2] $end
$upscope $end
$scope begin genblk1[3] $end
$upscope $end
$scope begin genblk1[4] $end
$upscope $end
$scope begin genblk1[5] $end
$upscope $end
$scope begin genblk1[6] $end
$upscope $end
$scope begin genblk1[7] $end
$upscope $end
$scope begin genblk1[8] $end
$upscope $end
$scope begin genblk1[9] $end
$upscope $end
$scope begin genblk1[10] $end
$upscope $end
$scope begin genblk1[11] $end
$upscope $end
$scope begin genblk1[12] $end
$upscope $end
$scope begin genblk1[13] $end
$upscope $end
$scope begin genblk1[14] $end
$upscope $end
$scope begin genblk1[15] $end
$upscope $end
$scope begin genblk1[16] $end
$upscope $end
$scope begin genblk1[17] $end
$upscope $end
$scope begin genblk1[18] $end
$upscope $end
$scope begin genblk1[19] $end
$upscope $end
$scope begin genblk1[20] $end
$upscope $end
$scope begin genblk1[21] $end
$upscope $end
$scope begin genblk1[22] $end
$upscope $end
$upscope $end
$upscope $end
$enddefinitions $end
#0
$dumpvars
b0 *
b0 )
b0 (
b0 '
b0 &
b0 %
1$
0#
b0 "
0!
$end
#3500
1!
#5000
1#
#7000
0!
#10000
0#
#10500
1!
#14000
0!
#15000
1#
#17500
1!
#20000
0#
0$
#21000
0!
#24500
b1 "
b1 )
1!
#25000
b1 &
b1 *
1#
#28000
0!
#30000
0#
#31500
b11 "
b10 )
1!
#35000
b1 %
b10 *
b1 '
b11 &
b1 (
0!
1#
#38500
b10 "
b11 )
1!
#40000
0#
#42000
0!
#45000
b10 %
b11 '
b10 &
b11 *
1#
#45500
b110 "
b100 )
1!
#49000
0!
#50000
0#
#52500
b111 "
b101 )
1!
#55000
b11 %
b100 *
b10 '
b111 &
1#
#56000
0!
#59500
b101 "
b110 )
1!
#60000
0#
#63000
0!
#65000
b101 %
b111 '
b101 &
b101 *
1#
#66500
b100 "
b111 )
1!
#70000
0!
0#
#73500
b1100 "
b1000 )
1!
#75000
b110 %
b110 *
b101 '
b1100 &
b0 (
1#
#77000
0!
#80000
0#
#80500
b1101 "
b1001 )
1!
#84000
0!
#85000
b1000 %
b1100 '
b1101 &
b111 *
1#
#87500
b1111 "
b1010 )
1!
#90000
0#
#91000
0!
#94500
b1110 "
b1011 )
1!
#95000
b1001 %
b1000 *
b1101 '
b1110 &
b1111111111111111111111111 (
1#
#98000
0!
#100000
0#
#101500
b1010 "
b1100 )
1!
#105000
b1011 %
b1110 '
b1010 &
b1001 *
0!
1#
#108500
b1011 "
b1101 )
1!
#110000
0#
#112000
0!
#115000
b1100 %
b1010 *
b1010 '
b1011 &
b1111111111111111111111110 (
1#
#115500
b1001 "
b1110 )
1!
#119000
0!
#120000
0#
#122500
b1000 "
b1111 )
1!
#125000
b1101 %
b1011 '
b1000 &
b1011 *
1#
#126000
0!
#129500
b11000 "
b10000 )
1!
#130000
0#
#133000
0!
#135000
b1111 %
b1100 *
b1000 '
b11000 &
1#
#136500
b11001 "
b10001 )
1!
#140000
0!
0#
#143500
b11011 "
b10010 )
1!
#145000
b10000 %
b1111111111111111111111101 (
b11000 '
b11011 &
b1101 *
1#
#147000
0!
#150000
0#
#150500
b11010 "
b10011 )
1!
#154000
0!
#155000
b10010 %
b1110 *
b11011 '
b11010 &
1#
#157500
b11110 "
b10100 )
1!
#160000
0#
#161000
0!
#164500
b11111 "
b10101 )
1!
#165000
b10011 %
b1111111111111111111111100 (
b11010 '
b11111 &
b1111 *
1#
#168000
0!
#170000
0#
#171500
b11101 "
b10110 )
1!
#175000
b10101 %
b10000 *
b11111 '
b11101 &
0!
1#
#178500
b11100 "
b10111 )
1!
#180000
0#
#182000
0!
#185000
b10110 %
b1111111111111111111111011 (
b11101 '
b11100 &
b10001 *
1#
#185500
b10100 "
b11000 )
1!
#189000
0!
#190000
0#
#192500
b10101 "
b11001 )
1!
#195000
b10111 %
b10010 *
b11100 '
b10101 &
1#
#196000
0!
#199500
b10111 "
b11010 )
1!
#200000
0#
#203000
0!
#205000
b11001 %
b10101 '
b10111 &
b10011 *
1#
#206500
b10110 "
b11011 )
1!
#210000
0!
0#
#213500
b10010 "
b11100 )
1!
#215000
b11010 %
b10100 *
b10111 '
b10010 &
b1111111111111111111111010 (
1#
#217000
0!
#220000
0#
#220500
b10011 "
b11101 )
1!
#224000
0!
#225000
b11100 %
b10010 '
b10011 &
b10101 *
1#
#227500
b10001 "
b11110 )
1!
#230000
0#
#231000
0!
#234500
b10000 "
b11111 )
1!
#235000
b11101 %
b10110 *
b10011 '
b10000 &
b1111111111111111111111001 (
1#
#238000
0!
#240000
0#
#241500
b110000 "
b100000 )
1!
#245000
b11111 %
b10000 '
b110000 &
b10111 *
0!
1#
#248500
b110001 "
b100001 )
1!
#250000
0#
#252000
0!
#255000
b100000 %
b11000 *
b110000 '
b110001 &
b1111111111111111111111000 (
1#
#255500
b110011 "
b100010 )
1!
#259000
0!
#260000
0#
#262500
b110010 "
b100011 )
1!
#265000
b100001 %
b110001 '
b110010 &
b11001 *
1#
#266000
0!
#269500
b110110 "
b100100 )
1!
#270000
0#
#273000
0!
#275000
b100011 %
b11010 *
b110010 '
b110110 &
1#
#276500
b110111 "
b100101 )
1!
#280000
0!
0#
#283500
b110101 "
b100110 )
1!
#285000
b100100 %
b1111111111111111111110111 (
b110110 '
b110101 &
b11011 *
1#
#287000
0!
#290000
0#
#290500
b110100 "
b100111 )
1!
#294000
0!
#295000
b100110 %
b11100 *
b110101 '
b110100 &
1#
#297500
b111100 "
b101000 )
1!
#300000
0#
#301000
0!
#304500
b111101 "
b101001 )
1!
#305000
b100111 %
b1111111111111111111110110 (
b110100 '
b111101 &
b11101 *
1#
#308000
0!
#310000
0#
#311500
b111111 "
b101010 )
1!
#315000
b101001 %
b11110 *
b111101 '
b111111 &
0!
1#
#318500
b111110 "
b101011 )
1!
#320000
0#
#322000
0!
#325000
b101010 %
b1111111111111111111110101 (
b111111 '
b111110 &
b11111 *
1#
#325500
b111010 "
b101100 )
1!
#329000
0!
#330000
0#
#332500
b111011 "
b101101 )
1!
#335000
b101011 %
b100000 *
b111110 '
b111011 &
1#
#336000
0!
#339500
b111001 "
b101110 )
1!
#340000
0#
#343000
0!
#345000
b101101 %
b111011 '
b111001 &
b100001 *
1#
#346500
b111000 "
b101111 )
1!
#350000
0!
0#
#353500
b101000 "
b110000 )
1!
#355000
b101110 %
b100010 *
b111001 '
b101000 &
b1111111111111111111110100 (
1#
#357000
0!
#360000
0#
#360500
b101001 "
b110001 )
1!
#364000
0!
#365000
b110000 %
b101000 '
b101001 &
b100011 *
1#
#367500
b101011 "
b110010 )
1!
#370000
0#
#371000
0!
#374500
b101010 "
b110011 )
1!
#375000
b110001 %
b100100 *
b101001 '
b101010 &
b1111111111111111111110011 (
1#
#378000
0!
#380000
0#
#381500
b101110 "
b110100 )
1!
#385000
b110011 %
b101010 '
b101110 &
b100101 *
0!
1#
#388500
b101111 "
b110101 )
1!
#390000
0#
#392000
0!
#395000
b110100 %
b100110 *
b101110 '
b101111 &
b1111111111111111111110010 (
1#
#395500
b101101 "
b110110 )
1!
#399000
0!
#400000
0#
#402500
b101100 "
b110111 )
1!
#405000
b110101 %
b101111 '
b101100 &
b100111 *
1#
#406000
0!
#409500
b100100 "
b111000 )
1!
#410000
0#
#413000
0!
#415000
b110111 %
b101000 *
b101100 '
b100100 &
1#
#416500
b100101 "
b111001 )
1!
#420000
0!
0#
#423500
b100111 "
b111010 )
1!
#425000
b111000 %
b1111111111111111111110001 (
b100100 '
b100111 &
b101001 *
1#
#427000
0!
#430000
0#
#430500
b100110 "
b111011 )
1!
#434000
0!
#435000
b111010 %
b101010 *
b100111 '
b100110 &
1#
#437500
b100010 "
b111100 )
1!
#440000
0#
#441000
0!
#444500
b100011 "
b111101 )
1!
#445000
b111011 %
b1111111111111111111110000 (
b100110 '
b100011 &
b101011 *
1#
#448000
0!
#450000
0#
#451500
b100001 "
b111110 )
1!
#455000
b111101 %
b101100 *
b100011 '
b100001 &
0!
1#
#458500
b100000 "
b111111 )
1!
#460000
0#
#462000
0!
#465000
b111110 %
b1111111111111111111101111 (
b100001 '
b100000 &
b101101 *
1#
#465500
b1100000 "
b1000000 )
1!
#469000
0!
#470000
0#
#472500
b1100001 "
b1000001 )
1!
#475000
b111111 %
b101110 *
b100000 '
b1100001 &
1#
#476000
0!
#479500
b1100011 "
b1000010 )
1!
#480000
0#
#483000
0!
#485000
b1000001 %
b1100001 '
b1100011 &
b101111 *
1#
#486500
b1100010 "
b1000011 )
1!
#490000
0!
0#
#493500
b1100110 "
b1000100 )
1!
#495000
b1000010 %
b110000 *
b1100011 '
b1100110 &
b1111111111111111111101110 (
1#
#497000
0!
#500000
0#
#500500
b1100111 "
b1000101 )
1!
#504000
0!
#505000
b1000100 %
b1100110 '
b1100111 &
b110001 *
1#
#507500
b1100101 "
b1000110 )
1!
#510000
0#
#511000
0!
#514500
b1100100 "
b1000111 )
1!
#515000
b1000101 %
b110010 *
b1100111 '
b1100100 &
b1111111111111111111101101 (
1#
#518000
0!
#520000
0#
#521500
b1101100 "
b1001000 )
1!
#525000
b1000111 %
b1100100 '
b1101100 &
b110011 *
0!
1#
#528500
b1101101 "
b1001001 )
1!
#530000
0#
#532000
0!
#535000
b1001000 %
b110100 *
b1101100 '
b1101101 &
b1111111111111111111101100 (
1#
#535500
b1101111 "
b1001010 )
1!
#539000
0!
#540000
0#
#542500
b1101110 "
b1001011 )
1!
#545000
b1001001 %
b1101101 '
b1101110 &
b110101 *
1#
#546000
0!
#549500
b1101010 "
b1001100 )
1!
#550000
0#
#553000
0!
#555000
b1001011 %
b110110 *
b1101110 '
b1101010 &
1#
#556500
b1101011 "
b1001101 )
1!
#560000
0!
0#
#563500
b1101001 "
b1001110 )
1!
#565000
b1001100 %
b1111111111111111111101011 (
b1101010 '
b1101001 &
b110111 *
1#
#567000
0!
#570000
0#
#570500
b1101000 "
b1001111 )
1!
#574000
0!
#575000
b1001110 %
b111000 *
b1101001 '
b1101000 &
1#
#577500
b1111000 "
b1010000 )
1!
#580000
0#
#581000
0!
#584500
b1111001 "
b1010001 )
1!
#585000
b1001111 %
b1111111111111111111101010 (
b1101000 '
b1111001 &
b111001 *
1#
#588000
0!
#590000
0#
#591500
b1111011 "
b1010010 )
1!
#595000
b1010001 %
b111010 *
b1111001 '
b1111011 &
0!
1#
#598500
b1111010 "
b1010011 )
1!
#600000
0#
#602000
0!
#605000
b1010010 %
b1111111111111111111101001 (
b1111011 '
b1111010 &
b111011 *
1#
#605500
b1111110 "
b1010100 )
1!
#609000
0!
#610000
0#
#612500
b1111111 "
b1010101 )
1!
#615000
b1010011 %
b111100 *
b1111010 '
b1111111 &
1#
#616000
0!
#619500
b1111101 "
b1010110 )
1!
#620000
0#
#623000
0!
#625000
b1010101 %
b1111111 '
b1111101 &
b111101 *
1#
#626500
b1111100 "
b1010111 )
1!
#630000
0!
0#
#633500
b1110100 "
b1011000 )
1!
#635000
b1010110 %
b111110 *
b1111101 '
b1110100 &
b1111111111111111111101000 (
1#
#637000
0!
#640000
0#
#640500
b1110101 "
b1011001 )
1!
#644000
0!
#645000
b1011000 %
b1110100 '
b1110101 &
b111111 *
1#
#647500
b1110111 "
b1011010 )
1!
#650000
0#
#651000
0!
#654500
b1110110 "
b1011011 )
1!
#655000
b1011001 %
b1000000 *
b1110101 '
b1110110 &
b1111111111111111111100111 (
1#
#658000
0!
#660000
0#
#661500
b1110010 "
b1011100 )
1!
#665000
b1011011 %
b1110110 '
b1110010 &
b1000001 *
0!
1#
#668500
b1110011 "
b1011101 )
1!
#670000
0#
#672000
0!
#675000
b1011100 %
b1000010 *
b1110010 '
b1110011 &
b1111111111111111111100110 (
1#
#675500
b1110001 "
b1011110 )
1!
#679000
0!
#680000
0#
#682500
b1110000 "
b1011111 )
1!
#685000
b1011101 %
b1110011 '
b1110000 &
b1000011 *
1#
#686000
0!
#689500
b1010000 "
b1100000 )
1!
#690000
0#
#693000
0!
#695000
b1011111 %
b1000100 *
b1110000 '
b1010000 &
1#
#696500
b1010001 "
b1100001 )
1!
#700000
0!
0#
#703500
b1010011 "
b1100010 )
1!
#705000
b1100000 %
b1111111111111111111100101 (
b1010000 '
b1010011 &
b1000101 *
1#
#707000
0!
#710000
0#
#710500
b1010010 "
b1100011 )
1!
#714000
0!
#715000
b1100010 %
b1000110 *
b1010011 '
b1010010 &
1#
#717500
b1010110 "
b1100100 )
1!
#720000
0#
#721000
0!
#724500
b1010111 "
b1100101 )
1!
#725000
b1100011 %
b1111111111111111111100100 (
b1010010 '
b1010111 &
b1000111 *
1#
#728000
0!
#730000
0#
#731500
b1010101 "
b1100110 )
1!
#735000
b1100101 %
b1001000 *
b1010111 '
b1010101 &
0!
1#
#738500
b1010100 "
b1100111 )
1!
#740000
0#
#742000
0!
#745000
b1100110 %
b1111111111111111111100011 (
b1010101 '
b1010100 &
b1001001 *
1#
#745500
b1011100 "
b1101000 )
1!
#749000
0!
#750000
0#
#752500
b1011101 "
b1101001 )
1!
#755000
b1100111 %
b1001010 *
b1010100 '
b1011101 &
1#
#756000
0!
#759500
b1011111 "
b1101010 )
1!
#760000
0#
#763000
0!
#765000
b1101001 %
b1011101 '
b1011111 &
b1001011 *
1#
#766500
b1011110 "
b1101011 )
1!
#770000
0!
0#
#773500
b1011010 "
b1101100 )
1!
#775000
b1101010 %
b1001100 *
b1011111 '
b1011010 &
b1111111111111111111100010 (
1#
#777000
0!
#780000
0#
#780500
b1011011 "
b1101101 )
1!
#784000
0!
#785000
b1101100 %
b1011010 '
b1011011 &
b1001101 *
1#
#787500
b1011001 "
b1101110 )
1!
#790000
0#
#791000
0!
#794500
b1011000 "
b1101111 )
1!
#795000
b1101101 %
b1001110 *
b1011011 '
b1011000 &
b1111111111111111111100001 (
1#
#798000
0!
#800000
0#
#801500
b1001000 "
b1110000 )
1!
#805000
b1101111 %
b1011000 '
b1001000 &
b1001111 *
0!
1#
#808500
b1001001 "
b1110001 )
1!
#810000
0#
#812000
0!
#815000
b1110000 %
b1010000 *
b1001000 '
b1001001 &
b1111111111111111111100000 (
1#
#815500
b1001011 "
b1110010 )
1!
#819000
0!
#820000
0#
#822500
b1001010 "
b1110011 )
1!
#825000
b1110001 %
b1001001 '
b1001010 &
b1010001 *
1#
#826000
0!
#829500
b1001110 "
b1110100 )
1!
#830000
0#
#833000
0!
#835000
b1110011 %
b1010010 *
b1001010 '
b1001110 &
1#
#836500
b1001111 "
b1110101 )
1!
#840000
0!
0#
#843500
b1001101 "
b1110110 )
1!
#845000
b1110100 %
b1111111111111111111011111 (
b1001110 '
b1001101 &
b1010011 *
1#
#847000
0!
#850000
0#
#850500
b1001100 "
b1110111 )
1!
#854000
0!
#855000
b1110110 %
b1010100 *
b1001101 '
b1001100 &
1#
#857500
b1000100 "
b1111000 )
1!
#860000
0#
#861000
0!
#864500
b1000101 "
b1111001 )
1!
#865000
b1110111 %
b1111111111111111111011110 (
b1001100 '
b1000101 &
b1010101 *
1#
#868000
0!
#870000
0#
#871500
b1000111 "
b1111010 )
1!
#875000
b1111001 %
b1010110 *
b1000101 '
b1000111 &
0!
1#
#878500
b1000110 "
b1111011 )
1!
#880000
0#
#882000
0!
#885000
b1111010 %
b1111111111111111111011101 (
b1000111 '
b1000110 &
b1010111 *
1#
#885500
b1000010 "
b1111100 )
1!
#889000
0!
#890000
0#
#892500
b1000011 "
b1111101 )
1!
#895000
b1111011 %
b1011000 *
b1000110 '
b1000011 &
1#
#896000
0!
#899500
b1000001 "
b1111110 )
1!
#900000
0#
#903000
0!
#905000
b1111101 %
b1000011 '
b1000001 &
b1011001 *
1#
#906500
b1000000 "
b1111111 )
1!
#910000
0!
0#
#913500
b11000000 "
b10000000 )
1!
#915000
b1111110 %
b1011010 *
b1000001 '
b11000000 &
b1111111111111111111011100 (
1#
#917000
0!
#920000
0#
#920500
b11000001 "
b10000001 )
1!
#924000
0!
#925000
b10000000 %
b11000000 '
b11000001 &
b1011011 *
1#
#927500
b11000011 "
b10000010 )
1!
#930000
0#
#931000
0!
#934500
b11000010 "
b10000011 )
1!
#935000
b10000001 %
b1011100 *
b11000001 '
b11000010 &
b1111111111111111111011011 (
1#
#938000
0!
#940000
0#
#941500
b11000110 "
b10000100 )
1!
#945000
b10000011 %
b11000010 '
b11000110 &
b1011101 *
0!
1#
#948500
b11000111 "
b10000101 )
1!
#950000
0#
#952000
0!
#955000
b10000100 %
b1011110 *
b11000110 '
b11000111 &
b1111111111111111111011010 (
1#
#955500
b11000101 "
b10000110 )
1!
#959000
0!
#960000
0#
#962500
b11000100 "
b10000111 )
1!
#965000
b10000101 %
b11000111 '
b11000100 &
b1011111 *
1#
#966000
0!
#969500
b11001100 "
b10001000 )
1!
#970000
0#
#973000
0!
#975000
b10000111 %
b1100000 *
b11000100 '
b11001100 &
1#
#976500
b11001101 "
b10001001 )
1!
#980000
0!
0#
#983500
b11001111 "
b10001010 )
1!
#985000
b10001000 %
b1111111111111111111011001 (
b11001100 '
b11001111 &
b1100001 *
1#
#987000
0!
#990000
0#
#990500
b11001110 "
b10001011 )
1!
#994000
0!
#995000
b10001010 %
b1100010 *
b11001111 '
b11001110 &
1#
#997500
b11001010 "
b10001100 )
1!
#1000000
0#
#1001000
0!
#1004500
b11001011 "
b10001101 )
1!
#1005000
b10001011 %
b1111111111111111111011000 (
b11001110 '
b11001011 &
b1100011 *
1#
#1008000
0!
#1010000
0#
#1011500
b11001001 "
b10001110 )
1!
#1015000
b10001101 %
b1100100 *
b11001011 '
b11001001 &
0!
1#
#1018500
b11001000 "
b10001111 )
1!
#1020000
0#
#1022000
0!
#1025000
b10001110 %
b1111111111111111111010111 (
b11001001 '
b11001000 &
b1100101 *
1#
#1025500
b11011000 "
b10010000 )
1!
#1029000
0!
#1030000
0#
#1032500
b11011001 "
b10010001 )
1!
#1035000
b10001111 %
b1100110 *
b11001000 '
b11011001 &
1#
#1036000
0!
#1039500
b11011011 "
b10010010 )
1!
#1040000
0#
#1043000
0!
#1045000
b10010001 %
b11011001 '
b11011011 &
b1100111 *
1#
#1046500
b11011010 "
b10010011 )
1!
#1050000
0!
0#
#1053500
b11011110 "
b10010100 )
1!
#1055000
b10010010 %
b1101000 *
b11011011 '
b11011110 &
b1111111111111111111010110 (
1#
#1057000
0!
#1060000
0#
#1060500
b11011111 "
b10010101 )
1!
#1064000
0!
#1065000
b10010100 %
b11011110 '
b11011111 &
b1101001 *
1#
#1067500
b11011101 "
b10010110 )
1!
#1070000
0#
#1071000
0!
#1074500
b11011100 "
b10010111 )
1!
#1075000
b10010101 %
b1101010 *
b11011111 '
b11011100 &
b1111111111111111111010101 (
1#
#1078000
0!
#1080000
0#
#1081500
b11010100 "
b10011000 )
1!
#1085000
b10010111 %
b11011100 '
b11010100 &
b1101011 *
0!
1#
#1088500
b11010101 "
b10011001 )
1!
#1090000
0#
#1092000
0!
#1095000
b10011000 %
b1101100 *
b11010100 '
b11010101 &
b1111111111111111111010100 (
1#
#1095500
b11010111 "
b10011010 )
1!
#1099000
0!
#1100000
0#
#1102500
b11010110 "
b10011011 )
1!
#1105000
b10011001 %
b11010101 '
b11010110 &
b1101101 *
1#
#1106000
0!
#1109500
b11010010 "
b10011100 )
1!
#1110000
0#
#1113000
0!
#1115000
b10011011 %
b1101110 *
b11010110 '
b11010010 &
1#
#1116500
b11010011 "
b10011101 )
1!
#1120000
0!
0#
#1123500
b11010001 "
b10011110 )
1!
#1125000
b10011100 %
b1111111111111111111010011 (
b11010010 '
b11010001 &
b1101111 *
1#
#1127000
0!
#1130000
0#
#1130500
b11010000 "
b10011111 )
1!
#1134000
0!
#1135000
b10011110 %
b1110000 *
b11010001 '
b11010000 &
1#
#1137500
b11110000 "
b10100000 )
1!
#1140000
0#
#1141000
0!
#1144500
b11110001 "
b10100001 )
1!
#1145000
b10011111 %
b1111111111111111111010010 (
b11010000 '
b11110001 &
b1110001 *
1#
#1148000
0!
#1150000
0#
#1151500
b11110011 "
b10100010 )
1!
#1155000
b10100001 %
b1110010 *
b11110001 '
b11110011 &
0!
1#
#1158500
b11110010 "
b10100011 )
1!
#1160000
0#
#1162000
0!
#1165000
b10100010 %
b1111111111111111111010001 (
b11110011 '
b11110010 &
b1110011 *
1#
#1165500
b11110110 "
b10100100 )
1!
#1169000
0!
#1170000
0#
#1172500
b11110111 "
b10100101 )
1!
#1175000
b10100011 %
b1110100 *
b11110010 '
b11110111 &
1#
#1176000
0!
#1179500
b11110101 "
b10100110 )
1!
#1180000
0#
#1183000
0!
#1185000
b10100101 %
b11110111 '
b11110101 &
b1110101 *
1#
#1186500
b11110100 "
b10100111 )
1!
#1190000
0!
0#
#1193500
b11111100 "
b10101000 )
1!
#1195000
b10100110 %
b1110110 *
b11110101 '
b11111100 &
b1111111111111111111010000 (
1#
#1197000
0!
#1200000
0#
#1200500
b11111101 "
b10101001 )
1!
#1204000
0!
#1205000
b10101000 %
b11111100 '
b11111101 &
b1110111 *
1#
#1207500
b11111111 "
b10101010 )
1!
#1210000
0#
#1211000
0!
#1214500
b11111110 "
b10101011 )
1!
#1215000
b10101001 %
b1111000 *
b11111101 '
b11111110 &
b1111111111111111111001111 (
1#
#1218000
0!
#1220000
0#
#1221500
b11111010 "
b10101100 )
1!
#1225000
b10101011 %
b11111110 '
b11111010 &
b1111001 *
0!
1#
#1228500
b11111011 "
b10101101 )
1!
#1230000
0#
#1232000
0!
#1235000
b10101100 %
b1111010 *
b11111010 '
b11111011 &
b1111111111111111111001110 (
1#
#1235500
b11111001 "
b10101110 )
1!
#1239000
0!
#1240000
0#
#1242500
b11111000 "
b10101111 )
1!
#1245000
b10101101 %
b11111011 '
b11111000 &
b1111011 *
1#
#1246000
0!
#1249500
b11101000 "
b10110000 )
1!
#1250000
0#
#1253000
0!
#1255000
b10101111 %
b1111100 *
b11111000 '
b11101000 &
1#
#1256500
b11101001 "
b10110001 )
1!
#1260000
0!
0#
#1263500
b11101011 "
b10110010 )
1!
#1265000
b10110000 %
b1111111111111111111001101 (
b11101000 '
b11101011 &
b1111101 *
1#
#1267000
0!
#1270000
0#
#1270500
b11101010 "
b10110011 )
1!
#1274000
0!
#1275000
b10110010 %
b1111110 *
b11101011 '
b11101010 &
1#
#1277500
b11101110 "
b10110100 )
1!
#1280000
0#
#1281000
0!
#1284500
b11101111 "
b10110101 )
1!
#1285000
b10110011 %
b1111111111111111111001100 (
b11101010 '
b11101111 &
b1111111 *
1#
#1288000
0!
#1290000
0#
#1291500
b11101101 "
b10110110 )
1!
#1295000
b10110101 %
b10000000 *
b11101111 '
b11101101 &
0!
1#
#1298500
b11101100 "
b10110111 )
1!
#1300000
0#
#1302000
0!
#1305000
b10110110 %
b1111111111111111111001011 (
b11101101 '
b11101100 &
b10000001 *
1#
#1305500
b11100100 "
b10111000 )
1!
#1309000
0!
#1310000
0#
#1312500
b11100101 "
b10111001 )
1!
#1315000
b10110111 %
b10000010 *
b11101100 '
b11100101 &
1#
#1316000
0!
#1319500
b11100111 "
b10111010 )
1!
#1320000
0#
#1323000
0!
#1325000
b10111001 %
b11100101 '
b11100111 &
b10000011 *
1#
#1326500
b11100110 "
b10111011 )
1!
#1330000
0!
0#
#1333500
b11100010 "
b10111100 )
1!
#1335000
b10111010 %
b10000100 *
b11100111 '
b11100010 &
b1111111111111111111001010 (
1#
#1337000
0!
#1340000
0#
#1340500
b11100011 "
b10111101 )
1!
#1344000
0!
#1345000
b10111100 %
b11100010 '
b11100011 &
b10000101 *
1#
#1347500
b11100001 "
b10111110 )
1!
#1350000
0#
#1351000
0!
#1354500
b11100000 "
b10111111 )
1!
#1355000
b10111101 %
b10000110 *
b11100011 '
b11100000 &
b1111111111111111111001001 (
1#
#1358000
0!
#1360000
0#
#1361500
b10100000 "
b11000000 )
1!
#1365000
b10111111 %
b11100000 '
b10100000 &
b10000111 *
0!
1#
#1368500
b10100001 "
b11000001 )
1!
#1370000
0#
#1372000
0!
#1375000
b11000000 %
b10001000 *
b10100000 '
b10100001 &
b1111111111111111111001000 (
1#
#1375500
b10100011 "
b11000010 )
1!
#1379000
0!
#1380000
0#
#1382500
b10100010 "
b11000011 )
1!
#1385000
b11000001 %
b10100001 '
b10100010 &
b10001001 *
1#
#1386000
0!
#1389500
b10100110 "
b11000100 )
1!
#1390000
0#
#1393000
0!
#1395000
b11000011 %
b10001010 *
b10100010 '
b10100110 &
1#
#1396500
b10100111 "
b11000101 )
1!
#1400000
0!
0#
#1403500
b10100101 "
b11000110 )
1!
#1405000
b11000100 %
b1111111111111111111000111 (
b10100110 '
b10100101 &
b10001011 *
1#
#1407000
0!
#1410000
0#
#1410500
b10100100 "
b11000111 )
1!
#1414000
0!
#1415000
b11000110 %
b10001100 *
b10100101 '
b10100100 &
1#
#1417500
b10101100 "
b11001000 )
1!
#1420000
0#
#1421000
0!
#1424500
b10101101 "
b11001001 )
1!
#1425000
b11000111 %
b1111111111111111111000110 (
b10100100 '
b10101101 &
b10001101 *
1#
#1428000
0!
#1430000
0#
#1431500
b10101111 "
b11001010 )
1!
#1435000
b11001001 %
b10001110 *
b10101101 '
b10101111 &
0!
1#
#1438500
b10101110 "
b11001011 )
1!
#1440000
0#
#1442000
0!
#1445000
b11001010 %
b1111111111111111111000101 (
b10101111 '
b10101110 &
b10001111 *
1#
#1445500
b10101010 "
b11001100 )
1!
#1449000
0!
#1450000
0#
#1452500
b10101011 "
b11001101 )
1!
#1455000
b11001011 %
b10010000 *
b10101110 '
b10101011 &
1#
#1456000
0!
#1459500
b10101001 "
b11001110 )
1!
#1460000
0#
#1463000
0!
#1465000
b11001101 %
b10101011 '
b10101001 &
b10010001 *
1#
#1466500
b10101000 "
b11001111 )
1!
#1470000
0!
0#
#1473500
b10111000 "
b11010000 )
1!
#1475000
b11001110 %
b10010010 *
b10101001 '
b10111000 &
b1111111111111111111000100 (
1#
#1477000
0!
#1480000
0#
#1480500
b10111001 "
b11010001 )
1!
#1484000
0!
#1485000
b11010000 %
b10111000 '
b10111001 &
b10010011 *
1#
#1487500
b10111011 "
b11010010 )
1!
#1490000
0#
#1491000
0!
#1494500
b10111010 "
b11010011 )
1!
#1495000
b11010001 %
b10010100 *
b10111001 '
b10111010 &
b1111111111111111111000011 (
1#
#1498000
0!
#1500000
0#
#1501500
b10111110 "
b11010100 )
1!
#1505000
b11010011 %
b10111010 '
b10111110 &
b10010101 *
0!
1#
#1508500
b10111111 "
b11010101 )
1!
#1510000
0#
#1512000
0!
#1515000
b11010100 %
b10010110 *
b10111110 '
b10111111 &
b1111111111111111111000010 (
1#
#1515500
b10111101 "
b11010110 )
1!
#1519000
0!
#1520000
0#
#1522500
b10111100 "
b11010111 )
1!
#1525000
b11010101 %
b10111111 '
b10111100 &
b10010111 *
1#
#1526000
0!
#1529500
b10110100 "
b11011000 )
1!
#1530000
0#
#1533000
0!
#1535000
b11010111 %
b10011000 *
b10111100 '
b10110100 &
1#
