ADPLL_scaled_v4/phase_detector.v
module phase_detector(
    input ref_clk,
    input fb_clk,
    input rst,
    output reg signed [24:0]phase_error
);

reg [23:0] phase_ref;

//Reference phase accumulator
always@(posedge ref_clk or posedge rst) begin
    if(rst)
        phase_ref <= 24'd0;
    else 
        phase_ref <= phase_ref + 24'd1;
end

//Feedback phase accumulator
reg[23:0] phase_fb_bin;
always@(posedge fb_clk or posedge rst) begin
    if(rst)
        phase_fb_bin <= 24'd0;
    else 
        phase_fb_bin <= phase_fb_bin + 24'd1;
end

//Binary to gray code
wire [23:0]phase_fb_gray;
assign phase_fb_gray = (phase_fb_bin) ^ (phase_fb_bin >> 1);

//2-FF synchronizer
reg [23:0]gray_sync1;
reg [23:0]gray_sync2;

always@(posedge ref_clk or posedge rst) begin
    if(rst) begin
        gray_sync1 <= 24'd0;
        gray_sync2 <= 24'd0;
    end
    else begin
        gray_sync1 <= phase_fb_gray;
        gray_sync2 <= gray_sync1;
    end
end

//Gray to Binary
wire [23:0]phase_fb_bin_sync;
genvar i;
generate 
    assign phase_fb_bin_sync[23] = gray_sync2[23];
    for(i = 22; i>=0; i=i-1)
        assign phase_fb_bin_sync[i] = phase_fb_bin_sync[i+1] ^ gray_sync2[i];
endgenerate

//Phase error calculation
always@(posedge ref_clk or posedge rst) begin
    if(rst)
        phase_error <= 25'sd0;
    else
        phase_error <= $signed({1'b0,phase_ref}) - $signed({1'b0,phase_fb_bin_sync});
end

endmodule

ADPLL_Integrated/adpll_top.v
module adpll_top(
    input ref_clk,
    input fb_clk,
    input rst,
    output signed [24:0]phase_error
);

phase_detector pd_inst(.ref_clk(ref_clk), .fb_clk(fb_clk), .rst(rst), .phase_error(phase_error));


endmodule

ADPLL_Integrated/tb_adpll_top.v
`timescale 1ns/1ps

module tb_adpll_top();

    reg ref_clk;
    reg fb_clk;
    reg rst;

    wire signed [24:0]phase_error;

    adpll_top dut(.ref_clk(ref_clk), .fb_clk(fb_clk), .rst(rst), .phase_error(phase_error));

    initial begin 
        ref_clk = 1'b0;
        fb_clk = 1'b0;
    end

    always #5 ref_clk = ~ref_clk;

    always #4 fb_clk = ~fb_clk;

    initial begin 
        $monitor("t=%0t rst=%b phase_error=%0d", $time, rst, phase_error);
    end

    initial begin 

        $dumpfile("test.vcd");
        $dumpvars(0,dut);

        rst = 1'b1;
        #20
        rst = 1'b0;

        #2000

        $finish;
    end

endmodule

ADPLL_Integrated/test.vcd
$date
	Sat Jun 20 23:38:47 2026
$end
$version
	Icarus Verilog
$end
$timescale
	1ps
$end
$scope module tb_adpll_top $end
$scope module dut $end
$var wire 1 ! fb_clk $end
$var wire 1 " ref_clk $end
$var wire 1 # rst $end
$var wire 25 $ phase_error [24:0] $end
$scope module pd_inst $end
$var wire 1 ! fb_clk $end
$var wire 24 % phase_fb_gray [23:0] $end
$var wire 1 " ref_clk $end
$var wire 1 # rst $end
$var wire 24 & phase_fb_bin_sync [23:0] $end
$var reg 24 ' gray_sync1 [23:0] $end
$var reg 24 ( gray_sync2 [23:0] $end
$var reg 25 ) phase_error [24:0] $end
$var reg 24 * phase_fb_bin [23:0] $end
$var reg 24 + phase_ref [23:0] $end
$scope begin genblk1[0] $end
$upscope $end
$scope begin genblk1[1] $end
$upscope $end
$scope begin genblk1[2] $end
$upscope $end
$scope begin genblk1[3] $end
$upscope $end
$scope begin genblk1[4] $end
$upscope $end
$scope begin genblk1[5] $end
$upscope $end
$scope begin genblk1[6] $end
$upscope $end
$scope begin genblk1[7] $end
$upscope $end
$scope begin genblk1[8] $end
$upscope $end
$scope begin genblk1[9] $end
$upscope $end
$scope begin genblk1[10] $end
$upscope $end
$scope begin genblk1[11] $end
$upscope $end
$scope begin genblk1[12] $end
$upscope $end
$scope begin genblk1[13] $end
$upscope $end
$scope begin genblk1[14] $end
$upscope $end
$scope begin genblk1[15] $end
$upscope $end
$scope begin genblk1[16] $end
$upscope $end
$scope begin genblk1[17] $end
$upscope $end
$scope begin genblk1[18] $end
$upscope $end
$scope begin genblk1[19] $end
$upscope $end
$scope begin genblk1[20] $end
$upscope $end
$scope begin genblk1[21] $end
$upscope $end
$scope begin genblk1[22] $end
$upscope $end
$upscope $end
$upscope $end
$upscope $end
$enddefinitions $end
#0
$dumpvars
b0 +
b0 *
b0 )
b0 (
b0 '
b0 &
b0 %
b0 $
1#
0"
0!
$end
#4000
1!
#5000
1"
#8000
0!
#10000
0"
#12000
1!
#15000
1"
#16000
0!
#20000
b1 %
b1 *
1!
0"
0#
#24000
0!
#25000
b1 '
b1 +
1"
#28000
b11 %
b10 *
1!
#30000
0"
#32000
0!
#35000
b1 &
b10 +
b1 (
b11 '
b1 $
b1 )
1"
#36000
b10 %
b11 *
1!
#40000
0!
0"
#44000
b110 %
b100 *
1!
#45000
b10 &
b11 (
b110 '
b11 +
1"
#48000
0!
#50000
0"
#52000
b111 %
b101 *
1!
#55000
b100 &
b100 +
b110 (
b111 '
1"
#56000
0!
#60000
b101 %
b110 *
1!
0"
#64000
0!
#65000
b101 &
b0 $
b0 )
b111 (
b101 '
b101 +
1"
#68000
b100 %
b111 *
1!
#70000
0"
#72000
0!
#75000
b110 &
b110 +
b101 (
b100 '
1"
#76000
b1100 %
b1000 *
1!
#80000
0!
0"
#84000
b1101 %
b1001 *
1!
#85000
b111 &
b100 (
b1101 '
b111 +
1"
#88000
0!
#90000
0"
#92000
b1111 %
b1010 *
1!
#95000
b1001 &
b1000 +
b1101 (
b1111 '
1"
#96000
0!
#100000
b1110 %
b1011 *
1!
0"
#104000
0!
#105000
b1010 &
b1111111111111111111111111 $
b1111111111111111111111111 )
b1111 (
b1110 '
b1001 +
1"
#108000
b1010 %
b1100 *
1!
#110000
0"
#112000
0!
#115000
b1011 &
b1010 +
b1110 (
b1010 '
1"
#116000
b1011 %
b1101 *
1!
#120000
0!
0"
#124000
b1001 %
b1110 *
1!
#125000
b1100 &
b1010 (
b1001 '
b1011 +
1"
#128000
0!
#130000
0"
#132000
b1000 %
b1111 *
1!
#135000
b1110 &
b1100 +
b1001 (
b1000 '
1"
#136000
0!
#140000
b11000 %
b10000 *
1!
0"
#144000
0!
#145000
b1111 &
b1111111111111111111111110 $
b1111111111111111111111110 )
b1000 (
b11000 '
b1101 +
1"
#148000
b11001 %
b10001 *
1!
#150000
0"
#152000
0!
#155000
b10000 &
b1110 +
b11000 (
b11001 '
1"
#156000
b11011 %
b10010 *
1!
#160000
0!
0"
#164000
b11010 %
b10011 *
1!
#165000
b10001 &
b11001 (
b11010 '
b1111 +
1"
#168000
0!
#170000
0"
#172000
b11110 %
b10100 *
1!
#175000
b10011 &
b10000 +
b11010 (
b11110 '
1"
#176000
0!
#180000
b11111 %
b10101 *
1!
0"
#184000
0!
#185000
b10100 &
b1111111111111111111111101 $
b1111111111111111111111101 )
b11110 (
b11111 '
b10001 +
1"
#188000
b11101 %
b10110 *
1!
#190000
0"
#192000
0!
#195000
b10101 &
b10010 +
b11111 (
b11101 '
1"
#196000
b11100 %
b10111 *
1!
#200000
0!
0"
#204000
b10100 %
b11000 *
1!
#205000
b10110 &
b11101 (
b10100 '
b10011 +
1"
#208000
0!
#210000
0"
#212000
b10101 %
b11001 *
1!
#215000
b11000 &
b10100 +
b10100 (
b10101 '
1"
#216000
0!
#220000
b10111 %
b11010 *
1!
0"
#224000
0!
#225000
b11001 &
b1111111111111111111111100 $
b1111111111111111111111100 )
b10101 (
b10111 '
b10101 +
1"
#228000
b10110 %
b11011 *
1!
#230000
0"
#232000
0!
#235000
b11010 &
b10110 +
b10111 (
b10110 '
1"
#236000
b10010 %
b11100 *
1!
#240000
0!
0"
#244000
b10011 %
b11101 *
1!
#245000
b11011 &
b10110 (
b10011 '
b10111 +
1"
#248000
0!
#250000
0"
#252000
b10001 %
b11110 *
1!
#255000
b11101 &
b11000 +
b10011 (
b10001 '
1"
#256000
0!
#260000
b10000 %
b11111 *
1!
0"
#264000
0!
#265000
b11110 &
b1111111111111111111111011 $
b1111111111111111111111011 )
b10001 (
b10000 '
b11001 +
1"
#268000
b110000 %
b100000 *
1!
#270000
0"
#272000
0!
#275000
b11111 &
b11010 +
b10000 (
b110000 '
1"
#276000
b110001 %
b100001 *
1!
#280000
0!
0"
#284000
b110011 %
b100010 *
1!
#285000
b100000 &
b110000 (
b110011 '
b11011 +
1"
#288000
0!
#290000
0"
#292000
b110010 %
b100011 *
1!
#295000
b100010 &
b11100 +
b110011 (
b110010 '
1"
#296000
0!
#300000
b110110 %
b100100 *
1!
0"
#304000
0!
#305000
b100011 &
b1111111111111111111111010 $
b1111111111111111111111010 )
b110010 (
b110110 '
b11101 +
1"
#308000
b110111 %
b100101 *
1!
#310000
0"
#312000
0!
#315000
b100100 &
b11110 +
b110110 (
b110111 '
1"
#316000
b110101 %
b100110 *
1!
#320000
0!
0"
#324000
b110100 %
b100111 *
1!
#325000
b100101 &
b110111 (
b110100 '
b11111 +
1"
#328000
0!
#330000
0"
#332000
b111100 %
b101000 *
1!
#335000
b100111 &
b100000 +
b110100 (
b111100 '
1"
#336000
0!
#340000
b111101 %
b101001 *
1!
0"
#344000
0!
#345000
b101000 &
b1111111111111111111111001 $
b1111111111111111111111001 )
b111100 (
b111101 '
b100001 +
1"
#348000
b111111 %
b101010 *
1!
#350000
0"
#352000
0!
#355000
b101001 &
b100010 +
b111101 (
b111111 '
1"
#356000
b111110 %
b101011 *
1!
#360000
0!
0"
#364000
b111010 %
b101100 *
1!
#365000
b101010 &
b111111 (
b111010 '
b100011 +
1"
#368000
0!
#370000
0"
#372000
b111011 %
b101101 *
1!
#375000
b101100 &
b100100 +
b111010 (
b111011 '
1"
#376000
0!
#380000
b111001 %
b101110 *
1!
0"
#384000
0!
#385000
b101101 &
b1111111111111111111111000 $
b1111111111111111111111000 )
b111011 (
b111001 '
b100101 +
1"
#388000
b111000 %
b101111 *
1!
#390000
0"
#392000
0!
#395000
b101110 &
b100110 +
b111001 (
b111000 '
1"
#396000
b101000 %
b110000 *
1!
#400000
0!
0"
#404000
b101001 %
b110001 *
1!
#405000
b101111 &
b111000 (
b101001 '
b100111 +
1"
#408000
0!
#410000
0"
#412000
b101011 %
b110010 *
1!
#415000
b110001 &
b101000 +
b101001 (
b101011 '
1"
#416000
0!
#420000
b101010 %
b110011 *
1!
0"
#424000
0!
#425000
b110010 &
b1111111111111111111110111 $
b1111111111111111111110111 )
b101011 (
b101010 '
b101001 +
1"
#428000
b101110 %
b110100 *
1!
#430000
0"
#432000
0!
#435000
b110011 &
b101010 +
b101010 (
b101110 '
1"
#436000
b101111 %
b110101 *
1!
#440000
0!
0"
#444000
b101101 %
b110110 *
1!
#445000
b110100 &
b101110 (
b101101 '
b101011 +
1"
#448000
0!
#450000
0"
#452000
b101100 %
b110111 *
1!
#455000
b110110 &
b101100 +
b101101 (
b101100 '
1"
#456000
0!
#460000
b100100 %
b111000 *
1!
0"
#464000
0!
#465000
b110111 &
b1111111111111111111110110 $
b1111111111111111111110110 )
b101100 (
b100100 '
b101101 +
1"
#468000
b100101 %
b111001 *
1!
#470000
0"
#472000
0!
#475000
b111000 &
b101110 +
b100100 (
b100101 '
1"
#476000
b100111 %
b111010 *
1!
#480000
0!
0"
#484000
b100110 %
b111011 *
1!
#485000
b111001 &
b100101 (
b100110 '
b101111 +
1"
#488000
0!
#490000
0"
#492000
b100010 %
b111100 *
1!
#495000
b111011 &
b110000 +
b100110 (
b100010 '
1"
#496000
0!
#500000
b100011 %
b111101 *
1!
0"
#504000
0!
#505000
b111100 &
b1111111111111111111110101 $
b1111111111111111111110101 )
b100010 (
b100011 '
b110001 +
1"
#508000
b100001 %
b111110 *
1!
#510000
0"
#512000
0!
#515000
b111101 &
b110010 +
b100011 (
b100001 '
1"
#516000
b100000 %
b111111 *
1!
#520000
0!
0"
#524000
b1100000 %
b1000000 *
1!
#525000
b111110 &
b100001 (
b1100000 '
b110011 +
1"
#528000
0!
#530000
0"
#532000
b1100001 %
b1000001 *
1!
#535000
b1000000 &
b110100 +
b1100000 (
b1100001 '
1"
#536000
0!
#540000
b1100011 %
b1000010 *
1!
0"
#544000
0!
#545000
b1000001 &
b1111111111111111111110100 $
b1111111111111111111110100 )
b1100001 (
b1100011 '
b110101 +
1"
#548000
b1100010 %
b1000011 *
1!
#550000
0"
#552000
0!
#555000
b1000010 &
b110110 +
b1100011 (
b1100010 '
1"
#556000
b1100110 %
b1000100 *
1!
#560000
0!
0"
#564000
b1100111 %
b1000101 *
1!
#565000
b1000011 &
b1100010 (
b1100111 '
b110111 +
1"
#568000
0!
#570000
0"
#572000
b1100101 %
b1000110 *
1!
#575000
b1000101 &
b111000 +
b1100111 (
b1100101 '
1"
#576000
0!
#580000
b1100100 %
b1000111 *
1!
0"
#584000
0!
#585000
b1000110 &
b1111111111111111111110011 $
b1111111111111111111110011 )
b1100101 (
b1100100 '
b111001 +
1"
#588000
b1101100 %
b1001000 *
1!
#590000
0"
#592000
0!
#595000
b1000111 &
b111010 +
b1100100 (
b1101100 '
1"
#596000
b1101101 %
b1001001 *
1!
#600000
0!
0"
#604000
b1101111 %
b1001010 *
1!
#605000
b1001000 &
b1101100 (
b1101111 '
b111011 +
1"
#608000
0!
#610000
0"
#612000
b1101110 %
b1001011 *
1!
#615000
b1001010 &
b111100 +
b1101111 (
b1101110 '
1"
#616000
0!
#620000
b1101010 %
b1001100 *
1!
0"
#624000
0!
#625000
b1001011 &
b1111111111111111111110010 $
b1111111111111111111110010 )
b1101110 (
b1101010 '
b111101 +
1"
#628000
b1101011 %
b1001101 *
1!
#630000
0"
#632000
0!
#635000
b1001100 &
b111110 +
b1101010 (
b1101011 '
1"
#636000
b1101001 %
b1001110 *
1!
#640000
0!
0"
#644000
b1101000 %
b1001111 *
1!
#645000
b1001101 &
b1101011 (
b1101000 '
b111111 +
1"
#648000
0!
#650000
0"
#652000
b1111000 %
b1010000 *
1!
#655000
b1001111 &
b1000000 +
b1101000 (
b1111000 '
1"
#656000
0!
#660000
b1111001 %
b1010001 *
1!
0"
#664000
0!
#665000
b1010000 &
b1111111111111111111110001 $
b1111111111111111111110001 )
b1111000 (
b1111001 '
b1000001 +
1"
#668000
b1111011 %
b1010010 *
1!
#670000
0"
#672000
0!
#675000
b1010001 &
b1000010 +
b1111001 (
b1111011 '
1"
#676000
b1111010 %
b1010011 *
1!
#680000
0!
0"
#684000
b1111110 %
b1010100 *
1!
#685000
b1010010 &
b1111011 (
b1111110 '
b1000011 +
1"
#688000
0!
#690000
0"
#692000
b1111111 %
b1010101 *
1!
#695000
b1010100 &
b1000100 +
b1111110 (
b1111111 '
1"
#696000
0!
#700000
b1111101 %
b1010110 *
1!
0"
#704000
0!
#705000
b1010101 &
b1111111111111111111110000 $
b1111111111111111111110000 )
b1111111 (
b1111101 '
b1000101 +
1"
#708000
b1111100 %
b1010111 *
1!
#710000
0"
#712000
0!
#715000
b1010110 &
b1000110 +
b1111101 (
b1111100 '
1"
#716000
b1110100 %
b1011000 *
1!
#720000
0!
0"
#724000
b1110101 %
b1011001 *
1!
#725000
b1010111 &
b1111100 (
b1110101 '
b1000111 +
1"
#728000
0!
#730000
0"
#732000
b1110111 %
b1011010 *
1!
#735000
b1011001 &
b1001000 +
b1110101 (
b1110111 '
1"
#736000
0!
#740000
b1110110 %
b1011011 *
1!
0"
#744000
0!
#745000
b1011010 &
b1111111111111111111101111 $
b1111111111111111111101111 )
b1110111 (
b1110110 '
b1001001 +
1"
#748000
b1110010 %
b1011100 *
1!
#750000
0"
#752000
0!
#755000
b1011011 &
b1001010 +
b1110110 (
b1110010 '
1"
#756000
b1110011 %
b1011101 *
1!
#760000
0!
0"
#764000
b1110001 %
b1011110 *
1!
#765000
b1011100 &
b1110010 (
b1110001 '
b1001011 +
1"
#768000
0!
#770000
0"
#772000
b1110000 %
b1011111 *
1!
#775000
b1011110 &
b1001100 +
b1110001 (
b1110000 '
1"
#776000
0!
#780000
b1010000 %
b1100000 *
1!
0"
#784000
0!
#785000
b1011111 &
b1111111111111111111101110 $
b1111111111111111111101110 )
b1110000 (
b1010000 '
b1001101 +
1"
#788000
b1010001 %
b1100001 *
1!
#790000
0"
#792000
0!
#795000
b1100000 &
b1001110 +
b1010000 (
b1010001 '
1"
#796000
b1010011 %
b1100010 *
1!
#800000
0!
0"
#804000
b1010010 %
b1100011 *
1!
#805000
b1100001 &
b1010001 (
b1010010 '
b1001111 +
1"
#808000
0!
#810000
0"
#812000
b1010110 %
b1100100 *
1!
#815000
b1100011 &
b1010000 +
b1010010 (
b1010110 '
1"
#816000
0!
#820000
b1010111 %
b1100101 *
1!
0"
#824000
0!
#825000
b1100100 &
b1111111111111111111101101 $
b1111111111111111111101101 )
b1010110 (
b1010111 '
b1010001 +
1"
#828000
b1010101 %
b1100110 *
1!
#830000
0"
#832000
0!
#835000
b1100101 &
b1010010 +
b1010111 (
b1010101 '
1"
#836000
b1010100 %
b1100111 *
1!
#840000
0!
0"
#844000
b1011100 %
b1101000 *
1!
#845000
b1100110 &
b1010101 (
b1011100 '
b1010011 +
1"
#848000
0!
#850000
0"
#852000
b1011101 %
b1101001 *
1!
#855000
b1101000 &
b1010100 +
b1011100 (
b1011101 '
1"
#856000
0!
#860000
b1011111 %
b1101010 *
1!
0"
#864000
0!
#865000
b1101001 &
b1111111111111111111101100 $
b1111111111111111111101100 )
b1011101 (
b1011111 '
b1010101 +
1"
#868000
b1011110 %
b1101011 *
1!
#870000
0"
#872000
0!
#875000
b1101010 &
b1010110 +
b1011111 (
b1011110 '
1"
#876000
b1011010 %
b1101100 *
1!
#880000
0!
0"
#884000
b1011011 %
b1101101 *
1!
#885000
b1101011 &
b1011110 (
b1011011 '
b1010111 +
1"
#888000
0!
#890000
0"
#892000
b1011001 %
b1101110 *
1!
#895000
b1101101 &
b1011000 +
b1011011 (
b1011001 '
1"
#896000
0!
#900000
b1011000 %
b1101111 *
1!
0"
#904000
0!
#905000
b1101110 &
b1111111111111111111101011 $
b1111111111111111111101011 )
b1011001 (
b1011000 '
b1011001 +
1"
#908000
b1001000 %
b1110000 *
1!
#910000
0"
#912000
0!
#915000
b1101111 &
b1011010 +
b1011000 (
b1001000 '
1"
#916000
b1001001 %
b1110001 *
1!
#920000
0!
0"
#924000
b1001011 %
b1110010 *
1!
#925000
b1110000 &
b1001000 (
b1001011 '
b1011011 +
1"
#928000
0!
#930000
0"
#932000
b1001010 %
b1110011 *
1!
#935000
b1110010 &
b1011100 +
b1001011 (
b1001010 '
1"
#936000
0!
#940000
b1001110 %
b1110100 *
1!
0"
#944000
0!
#945000
b1110011 &
b1111111111111111111101010 $
b1111111111111111111101010 )
b1001010 (
b1001110 '
b1011101 +
1"
#948000
b1001111 %
b1110101 *
1!
#950000
0"
#952000
0!
#955000
b1110100 &
b1011110 +
b1001110 (
b1001111 '
1"
#956000
b1001101 %
b1110110 *
1!
#960000
0!
0"
#964000
b1001100 %
b1110111 *
1!
#965000
b1110101 &
b1001111 (
b1001100 '
b1011111 +
1"
#968000
0!
#970000
0"
#972000
b1000100 %
b1111000 *
1!
#975000
b1110111 &
b1100000 +
b1001100 (
b1000100 '
1"
#976000
0!
#980000
b1000101 %
b1111001 *
1!
0"
#984000
0!
#985000
b1111000 &
b1111111111111111111101001 $
b1111111111111111111101001 )
b1000100 (
b1000101 '
b1100001 +
1"
#988000
b1000111 %
b1111010 *
1!
#990000
0"
#992000
0!
#995000
b1111001 &
b1100010 +
b1000101 (
b1000111 '
1"
#996000
b1000110 %
b1111011 *
1!
#1000000
0!
0"
#1004000
b1000010 %
b1111100 *
1!
#1005000
b1111010 &
b1000111 (
b1000010 '
b1100011 +
1"
#1008000
0!
#1010000
0"
#1012000
b1000011 %
b1111101 *
1!
#1015000
b1111100 &
b1100100 +
b1000010 (
b1000011 '
1"
#1016000
0!
#1020000
b1000001 %
b1111110 *
1!
0"
#1024000
0!
#1025000
b1111101 &
b1111111111111111111101000 $
b1111111111111111111101000 )
b1000011 (
b1000001 '
b1100101 +
1"
#1028000
b1000000 %
b1111111 *
1!
#1030000
0"
#1032000
0!
#1035000
b1111110 &
b1100110 +
b1000001 (
b1000000 '
1"
#1036000
b11000000 %
b10000000 *
1!
#1040000
0!
0"
#1044000
b11000001 %
b10000001 *
1!
#1045000
b1111111 &
b1000000 (
b11000001 '
b1100111 +
1"
#1048000
0!
#1050000
0"
#1052000
b11000011 %
b10000010 *
1!
#1055000
b10000001 &
b1101000 +
b11000001 (
b11000011 '
1"
#1056000
0!
#1060000
b11000010 %
b10000011 *
1!
0"
#1064000
0!
#1065000
b10000010 &
b1111111111111111111100111 $
b1111111111111111111100111 )
b11000011 (
b11000010 '
b1101001 +
1"
#1068000
b11000110 %
b10000100 *
1!
#1070000
0"
#1072000
0!
#1075000
b10000011 &
b1101010 +
b11000010 (
b11000110 '
1"
#1076000
b11000111 %
b10000101 *
1!
#1080000
0!
0"
#1084000
b11000101 %
b10000110 *
1!
#1085000
b10000100 &
b11000110 (
b11000101 '
b1101011 +
1"
#1088000
0!
#1090000
0"
#1092000
b11000100 %
b10000111 *
1!
#1095000
b10000110 &
b1101100 +
b11000101 (
b11000100 '
1"
#1096000
0!
#1100000
b11001100 %
b10001000 *
1!
0"
#1104000
0!
#1105000
b10000111 &
b1111111111111111111100110 $
b1111111111111111111100110 )
b11000100 (
b11001100 '
b1101101 +
1"
#1108000
b11001101 %
b10001001 *
1!
#1110000
0"
#1112000
0!
#1115000
b10001000 &
b1101110 +
b11001100 (
b11001101 '
1"
#1116000
b11001111 %
b10001010 *
1!
#1120000
0!
0"
#1124000
b11001110 %
b10001011 *
1!
#1125000
b10001001 &
b11001101 (
b11001110 '
b1101111 +
1"
#1128000
0!
#1130000
0"
#1132000
b11001010 %
b10001100 *
1!
#1135000
b10001011 &
b1110000 +
b11001110 (
b11001010 '
1"
#1136000
0!
#1140000
b11001011 %
b10001101 *
1!
0"
#1144000
0!
#1145000
b10001100 &
b1111111111111111111100101 $
b1111111111111111111100101 )
b11001010 (
b11001011 '
b1110001 +
1"
#1148000
b11001001 %
b10001110 *
1!
#1150000
0"
#1152000
0!
#1155000
b10001101 &
b1110010 +
b11001011 (
b11001001 '
1"
#1156000
b11001000 %
b10001111 *
1!
#1160000
0!
0"
#1164000
b11011000 %
b10010000 *
1!
#1165000
b10001110 &
b11001001 (
b11011000 '
b1110011 +
1"
#1168000
0!
#1170000
0"
#1172000
b11011001 %
b10010001 *
1!
#1175000
b10010000 &
b1110100 +
b11011000 (
b11011001 '
1"
#1176000
0!
#1180000
b11011011 %
b10010010 *
1!
0"
#1184000
0!
#1185000
b10010001 &
b1111111111111111111100100 $
b1111111111111111111100100 )
b11011001 (
b11011011 '
b1110101 +
1"
#1188000
b11011010 %
b10010011 *
1!
#1190000
0"
#1192000
0!
#1195000
b10010010 &
b1110110 +
b11011011 (
b11011010 '
1"
#1196000
b11011110 %
b10010100 *
1!
#1200000
0!
0"
#1204000
b11011111 %
b10010101 *
1!
#1205000
b10010011 &
b11011010 (
b11011111 '
b1110111 +
1"
#1208000
0!
#1210000
0"
#1212000
b11011101 %
b10010110 *
1!
#1215000
b10010101 &
b1111000 +
b11011111 (
b11011101 '
1"
#1216000
0!
#1220000
b11011100 %
b10010111 *
1!
0"
#1224000
0!
#1225000
b10010110 &
b1111111111111111111100011 $
b1111111111111111111100011 )
b11011101 (
b11011100 '
b1111001 +
1"
#1228000
b11010100 %
b10011000 *
1!
#1230000
0"
#1232000
0!
#1235000
b10010111 &
b1111010 +
b11011100 (
b11010100 '
1"
#1236000
b11010101 %
b10011001 *
1!
#1240000
0!
0"
#1244000
b11010111 %
b10011010 *
1!
#1245000
b10011000 &
b11010100 (
b11010111 '
b1111011 +
1"
#1248000
0!
#1250000
0"
#1252000
b11010110 %
b10011011 *
1!
#1255000
b10011010 &
b1111100 +
b11010111 (
b11010110 '
1"
#1256000
0!
#1260000
b11010010 %
b10011100 *
1!
0"
#1264000
0!
#1265000
b10011011 &
b1111111111111111111100010 $
b1111111111111111111100010 )
b11010110 (
b11010010 '
b1111101 +
1"
#1268000
b11010011 %
b10011101 *
1!
#1270000
0"
#1272000
0!
#1275000
b10011100 &
b1111110 +
b11010010 (
b11010011 '
1"
#1276000
b11010001 %
b10011110 *
1!
#1280000
0!
0"
#1284000
b11010000 %
b10011111 *
1!
#1285000
b10011101 &
b11010011 (
b11010000 '
b1111111 +
1"
#1288000
0!
#1290000
0"
#1292000
b11110000 %
b10100000 *
1!
#1295000
b10011111 &
b10000000 +
b11010000 (
b11110000 '
1"
#1296000
0!
#1300000
b11110001 %
b10100001 *
1!
0"
#1304000
0!
#1305000
b10100000 &
b1111111111111111111100001 $
b1111111111111111111100001 )
b11110000 (
b11110001 '
b10000001 +
1"
#1308000
b11110011 %
b10100010 *
1!
#1310000
0"
#1312000
0!
#1315000
b10100001 &
b10000010 +
b11110001 (
b11110011 '
1"
#1316000
b11110010 %
b10100011 *
1!
#1320000
0!
0"
#1324000
b11110110 %
b10100100 *
1!
#1325000
b10100010 &
b11110011 (
b11110110 '
b10000011 +
1"
#1328000
0!
#1330000
0"
#1332000
b11110111 %
b10100101 *
1!
#1335000
b10100100 &
b10000100 +
b11110110 (
b11110111 '
1"
#1336000
0!
#1340000
b11110101 %
b10100110 *
1!
0"
#1344000
0!
#1345000
b10100101 &
b1111111111111111111100000 $
b1111111111111111111100000 )
b11110111 (
b11110101 '
b10000101 +
1"
#1348000
b11110100 %
b10100111 *
1!
#1350000
0"
#1352000
0!
#1355000
b10100110 &
b10000110 +
b11110101 (
b11110100 '
1"
#1356000
b11111100 %
b10101000 *
1!
#1360000
0!
0"
#1364000
b11111101 %
b10101001 *
1!
#1365000
b10100111 &
b11110100 (
b11111101 '
b10000111 +
1"
#1368000
0!
#1370000
0"
#1372000
b11111111 %
b10101010 *
1!
#1375000
b10101001 &
b10001000 +
b11111101 (
b11111111 '
1"
#1376000
0!
#1380000
b11111110 %
b10101011 *
1!
0"
#1384000
0!
#1385000
b10101010 &
b1111111111111111111011111 $
b1111111111111111111011111 )
b11111111 (
b11111110 '
b10001001 +
1"
#1388000
b11111010 %
b10101100 *
1!
#1390000
0"
#1392000
0!
#1395000
b10101011 &
b10001010 +
b11111110 (
b11111010 '
1"
#1396000
b11111011 %
b10101101 *
1!
#1400000
0!
0"
#1404000
b11111001 %
b10101110 *
1!
#1405000
b10101100 &
b11111010 (
b11111001 '
b10001011 +
1"
#1408000
0!
#1410000
0"
#1412000
b11111000 %
b10101111 *
1!
#1415000
b10101110 &
b10001100 +
b11111001 (
b11111000 '
1"
#1416000
0!
#1420000
b11101000 %
b10110000 *
1!
0"
#1424000
0!
#1425000
b10101111 &
b1111111111111111111011110 $
b1111111111111111111011110 )
b11111000 (
b11101000 '
b10001101 +
1"
#1428000
b11101001 %
b10110001 *
1!
#1430000
0"
#1432000
0!
#1435000
b10110000 &
b10001110 +
b11101000 (
b11101001 '
1"
#1436000
b11101011 %
b10110010 *
1!
#1440000
0!
0"
#1444000
b11101010 %
b10110011 *
1!
#1445000
b10110001 &
b11101001 (
b11101010 '
b10001111 +
1"
#1448000
0!
#1450000
0"
#1452000
b11101110 %
b10110100 *
1!
#1455000
b10110011 &
b10010000 +
b11101010 (
b11101110 '
1"
#1456000
0!
#1460000
b11101111 %
b10110101 *
1!
0"
#1464000
0!
#1465000
b10110100 &
b1111111111111111111011101 $
b1111111111111111111011101 )
b11101110 (
b11101111 '
b10010001 +
1"
#1468000
b11101101 %
b10110110 *
1!
#1470000
0"
#1472000
0!
#1475000
b10110101 &
b10010010 +
b11101111 (
b11101101 '
1"
#1476000
b11101100 %
b10110111 *
1!
#1480000
0!
0"
#1484000
b11100100 %
b10111000 *
1!
#1485000
b10110110 &
b11101101 (
b11100100 '
b10010011 +
1"
#1488000
0!
#1490000
0"
#1492000
b11100101 %
b10111001 *
1!
#1495000
b10111000 &
b10010100 +
b11100100 (
b11100101 '
1"
#1496000
0!
#1500000
b11100111 %
b10111010 *
1!
0"
#1504000
0!
#1505000
b10111001 &
b1111111111111111111011100 $
b1111111111111111111011100 )
b11100101 (
b11100111 '
b10010101 +
1"
#1508000
b11100110 %
b10111011 *
1!
#1510000
0"
#1512000
0!
#1515000
b10111010 &
b10010110 +
b11100111 (
b11100110 '
1"
#1516000
b11100010 %
b10111100 *
1!
#1520000
0!
0"
#1524000
b11100011 %
b10111101 *
1!
#1525000
b10111011 &
b11100110 (
b11100011 '
b10010111 +
1"
#1528000
0!
#1530000
0"
#1532000
b11100001 %
b10111110 *
1!
#1535000
b10111101 &
b10011000 +
b11100011 (
b11100001 '
1"
#1536000
0!
#1540000
b11100000 %
b10111111 *
1!
0"
#1544000
0!
#1545000
b10111110 &
b1111111111111111111011011 $
b1111111111111111111011011 )
b11100001 (
b11100000 '
b10011001 +
1"
#1548000
b10100000 %
b11000000 *
1!
#1550000
0"
#1552000
0!
#1555000
b10111111 &
b10011010 +
b11100000 (
b10100000 '
1"
#1556000
b10100001 %
b11000001 *
1!
#1560000
0!
0"
#1564000
b10100011 %
b11000010 *
1!
#1565000
b11000000 &
b10100000 (
b10100011 '
b10011011 +
1"
#1568000
0!
#1570000
0"
#1572000
b10100010 %
b11000011 *
1!
#1575000
b11000010 &
b10011100 +
b10100011 (
b10100010 '
1"
#1576000
0!
#1580000
b10100110 %
b11000100 *
1!
0"
#1584000
0!
#1585000
b11000011 &
b1111111111111111111011010 $
b1111111111111111111011010 )
b10100010 (
b10100110 '
b10011101 +
1"
#1588000
b10100111 %
b11000101 *
1!
#1590000
0"
#1592000
0!
#1595000
b11000100 &
b10011110 +
b10100110 (
b10100111 '
1"
#1596000
b10100101 %
b11000110 *
1!
#1600000
0!
0"
